Workbook

Sheet readme
B2: Total unique relationship | C2: where the other party is private | D2: with an scf match
B3: =COUNTIF(doublecounting!C3:D3579,">0")-SUM(doublecounting!E3:E3579) -> 3577 | D3: =COUNTIF(doublecounting!F3:G3579,">0")-SUM(doublecounting!H3:H3579) -> 980
B4: of which in target file
B5: =COUNTIF(doublecounting!C3:C3579,">0") -> 1932 | D5: =COUNTIF(doublecounting!F3:F3579,">0") -> 730
B6: of which in source file
B7: =COUNTIF(doublecounting!D3:D3579,">0") -> 1680 | D7: =COUNTIF(doublecounting!G3:G3579,">0") -> 256
B8: of which in both
B9: =SUM(doublecounting!E3:E3579) -> 35 | D9: =SUM(doublecounting!H3:H3579) -> 6
B10: ratio suppliers per buyer
B11: =readme!B3/COUNTA(has_scf!$E$2:$E$1366) -> 2.6205128 | D11: =readme!D3/COUNTIF(has_scf!F2:F1366,">0") -> 10

Sheet has_scf
A1: filing_id | B1: isin | C1: has_scf | E1: unique_isin
A2: 7742710 | B2: GB00B65TLW28 | C2: 0 | E2: GB00B65TLW28 | F2: =COUNTIFS($B$2:$B$40260,E2,$C$2:$C$40260,1) -> 0
A3: 7741925 | B3: GB00BLTVCF91 | C3: 0 | E3: GB00BLTVCF91 | F3: =COUNTIFS($B$2:$B$40260,E3,$C$2:$C$40260,1) -> 0
A4: 7741924 | B4: GB00BNDQJN14 | C4: 0 | E4: GB00BNDQJN14 | F4: =COUNTIFS($B$2:$B$40260,E4,$C$2:$C$40260,1) -> 0
A5: 7741923 | B5: GB00BYQ0JC66 | C5: 0 | E5: GB00BYQ0JC66 | F5: =COUNTIFS($B$2:$B$40260,E5,$C$2:$C$40260,1) -> 0
A6: 7741910 | B6: GB00BYX7MG58 | C6: 0 | E6: GB00BYX7MG58 | F6: =COUNTIFS($B$2:$B$40260,E6,$C$2:$C$40260,1) -> 0
A7: 7741888 | B7: GB0004270301 | C7: 0 | E7: GB0004270301 | F7: =COUNTIFS($B$2:$B$40260,E7,$C$2:$C$40260,1) -> 0
A8: 7741887 | B8: GB0000961622 | C8: 0 | E8: GB0000961622 | F8: =COUNTIFS($B$2:$B$40260,E8,$C$2:$C$40260,1) -> 1
A9: 7741886 | B9: GB0006825383 | C9: 0 | E9: GB0006825383 | F9: =COUNTIFS($B$2:$B$40260,E9,$C$2:$C$40260,1) -> 0
A10: 7741818 | B10: GB00BMDV1220 | C10: 0 | E10: GB00BMDV1220 | F10: =COUNTIFS($B$2:$B$40260,E10,$C$2:$C$40260,1) -> 1
A11: 7741810 | B11: GB00B45XLP34 | C11: 0 | E11: GB00B45XLP34 | F11: =COUNTIFS($B$2:$B$40260,E11,$C$2:$C$40260,1) -> 0
A12: 7741796 | B12: GB00B65TLW28 | C12: 0 | E12: GB00BDFGHW41 | F12: =COUNTIFS($B$2:$B$40260,E12,$C$2:$C$40260,1) -> 0
A13: 7740575 | B13: GB00BDFGHW41 | C13: 0 | E13: VGG368811037 | F13: =COUNTIFS($B$2:$B$40260,E13,$C$2:$C$40260,1) -> 0
... A1366: 6770498 | B1366: GB00BLR8L223 | C1366: 0 | E1366: GB00B01YQ796 | F1366: =COUNTIFS($B$2:$B$40260,E1366,$C$2:$C$40260,1) -> 0
A1367: 6770491 | B1367: GB0030181522 | C1367: 0
A1368: 6770484 | B1368: GB00B0358N07 | C1368: 0
A1369: 6770475 | B1369: GB0032089863 | C1369: 0
A1370: 6770470 | B1370: GB00B1VNSX38 | C1370: 0
A1371: 6770469 | B1371: GB00B00FPT80 | C1371: 0
A1372: 6770462 | B1372: GB0007922338 | C1372: 0
A1373: 6770459 | B1373: GB00BMD6PM55 | C1373: 0
A1374: 6770449 | B1374: GB00B8YZTJ80 | C1374: 0
A1375: 6770447 | B1375: GB0009580571 | C1375: 0
A1376: 6770436 | B1376: GB00BG0X1P77 | C1376: 0
A1377: 6770413 | B1377: GB0003062816 | C1377: 0
A1378: 5672330 | B1378: GB00BFYYT831 | C1378: 0
... A40260: 3201688 | B40260: GB00B0CJ9K73 | C40260: 0

Sheet target_uk
A1: rel_type | B1: column_4_doublecounting | C1: target_isin | D1: has_scf | E1: start_ | F1: id | G1: source_company_id | H1: target_company_id | I1: subsidiaries | J1: revenue_percent | K1: percent_estimated | L1: source_company_subsidiaries | M1: target_company_subsidiaries | N1: source_name | O1: source_ticker | P1: source_cusip | Q1: source_isin | R1: source_sedol | S1: target_name | T1: target_ticker | U1: target_cusip | V1: target_sedol | W1: source_company_keyword | X1: target_company_keyword | Y1: keyword1 | Z1: keyword2 | AA1: keyword3 | AB1: keyword4 | AC1: keyword5 | AD1: keyword6 | AE1: keyword7 | AF1: keyword8 | AG1: keyword9 | AH1: keyword10 | AI1: end_
A2: CUSTOMER | B2: =C2&IF(Q2="",W2,Q2) -> GB00BK9RKT01SE0000407991 | C2: GB00BK9RKT01 | D2: =SIGN(VLOOKUP(target_uk!C2,has_scf!$E$2:$F$1366,2,FALSE)) -> 1 | E2: 42709 | F2: CUST-101223503 | G2: 194503174 | H2: 1776804 | K2: Y | M2: City plumbing Supplies Holdings Ltd | N2: Svedbergs Group AB | O2: SVED.B | P2: W89736115 | Q2: SE0000407991 | R2: B12Z0T8 | S2: Travis Perkins Plc | T2: TPK | U2: G90202139 | V2: BK9RKT0 | W2: Svedbergs I Dalstorp | X2: City plumbing Supplies | AI2: 43963
A3: CUSTOMER | B3: =C3&IF(Q3="",W3,Q3) -> GB00BK9RKT01SE0000407991 | C3: GB00BK9RKT01 | D3: =SIGN(VLOOKUP(target_uk!C3,has_scf!$E$2:$F$1366,2,FALSE)) -> 1 | E3: 43963 | F3: CUST-101223503 | G3: 194503174 | H3: 1776804 | K3: Y | M3: City Plumbing Supplies Holdings Ltd | N3: Svedbergs Group AB | O3: SVED.B | P3: W89736115 | Q3: SE0000407991 | R3: B12Z0T8 | S3: Travis Perkins Plc | T3: TPK | U3: G90202139 | V3: BK9RKT0 | W3: Svedbergs I Dalstorp | X3: City plumbing Supplies | AI3: 44365
A4: CUSTOMER | B4: =C4&IF(Q4="",W4,Q4) -> GB00B3MBS747US84763R1014 | C4: GB00B3MBS747 | D4: =SIGN(VLOOKUP(target_uk!C4,has_scf!$E$2:$F$1366,2,FALSE)) -> 0 | E4: 42710 | F4: CUST-101300131 | G4: 8594 | H4: 194520295 | K4: Y | N4: Spectrum Brands Legacy, Inc. | O4: SPB.XX1 | P4: 84763R101 | Q4: US84763R1014 | R4: B3MYPN8 | S4: Ocado Group Plc | T4: OCDO | U4: G6718L106 | V4: B3MBS74 | W4: Spectrum Brands | X4: Ocado Group | Y4: Scale and Distribution | Z4: Europe | AI4: 767011
A5: CUSTOMER | B5: =C5&IF(Q5="",W5,Q5) -> GB00B012TP20US84763R1014 | C5: GB00B012TP20 | D5: =SIGN(VLOOKUP(target_uk!C5,has_scf!$E$2:$F$1366,2,FALSE)) -> 0 | E5: 42710 | F5: CUST-101300417 | G5: 8594 | H5: 1832300 | K5: Y | N5: Spectrum Brands Legacy, Inc. | O5: SPB.XX1 | P5: 84763R101 | Q5: US84763R1014 | R5: B3MYPN8 | S5: Halfords Group Plc | T5: HFD | U5: G4280E105 | V5: B012TP2 | W5: Spectrum Brands | X5: Halfords Group | Y5: Scale and Distribution | Z5: Europe | AI5: 767011
A6: CUSTOMER | B6: =C6&IF(Q6="",W6,Q6) -> GB00BRJQ8J25GB0009422543 | C6: GB00BRJQ8J25 | D6: =SIGN(VLOOKUP(target_uk!C6,has_scf!$E$2:$F$1366,2,FALSE)) -> 0 | E6: 42710 | F6: CUST-101320503 | G6: 1832545 | H6: 1832308 | K6: Y | N6: Waterman Group Plc | O6: WTM | P6: G94755108 | Q6: GB0009422543 | R6: 942254 | S6: Hammerson Plc | T6: HMSO | U6: G4273Q206 | V6: BRJQ8J2 | W6: Waterman Group | X6: Hammerson | Y6: structural | Z6: developer | AI6: 45583
A7: CUSTOMER | B7: =C7&IF(Q7="",W7,Q7) -> GB00B0744B38US6097201072 | C7: GB00B0744B38 | D7: =SIGN(VLOOKUP(target_uk!C7,has_scf!$E$2:$F$1366,2,FALSE)) -> 0 | E7: 42716 | F7: CUST-101524843 | G7: 6928 | H7: 1302 | K7: Y | M7: Bunzl Distribution Midcentral, Inc | N7: Monmouth Real Estate Investment Corp. | O7: MNR.XX10 | P7: 609720107 | Q7: US6097201072 | R7: 2504072 | S7: Bunzl Plc | T7: BNZL | U7: G16968110 | V7: B0744B3 | W7: Monmouth | X7: Bunzl Distribution Midcentral, Inc | Y7: Principal Tenants | AI7: 44171
A8: CUSTOMER | B8: =C8&IF(Q8="",W8,Q8) -> GB00B0744B38US6097201072 | C8: GB00B0744B38 | D8: =SIGN(VLOOKUP(target_uk!C8,has_scf!$E$2:$F$1366,2,FALSE)) -> 0 | E8: 44171 | F8: CUST-101524843 | G8: 6928 | H8: 1302 | J8: 0.46 | K8: Y | M8: Bunzl Distribution Midcentral, Inc | N8: Monmouth Real Estate Investment Corp. | O8: MNR.XX10 | P8: 609720107 | Q8: US6097201072 | R8: 2504072 | S8: Bunzl Plc | T8: BNZL | U8: G16968110 | V8: B0744B3 | W8: Monmouth | X8: Bunzl Distribution Midcentral, Inc | Y8: Principal Tenants | AI8: 44572
A9: CUSTOMER | B9: =C9&IF(Q9="",W9,Q9) -> GB00B1L5QH97MT0000780107 | C9: GB00B1L5QH97 | D9: =SIGN(VLOOKUP(target_uk!C9,has_scf!$E$2:$F$1366,2,FALSE)) -> 0 | E9: 43598 | F9: CUST-101588699 | G9: 16087650 | H9: 16033 | K9: Y | M9: Grosvenor Casinos Ltd. | N9: Kambi Group Plc | O9: KAMBI | P9: X4170A107 | Q9: MT0000780107 | R9: BMNQDC1 | S9: Rank Group Plc | T9: RNK | U9: G7377H121 | V9: B1L5QH9 | W9: kambi group plc | X9: Rank Group | AI9: 43969
A10: CUSTOMER | B10: =C10&IF(Q10="",W10,Q10) -> GB00B1L5QH97MT0000780107 | C10: GB00B1L5QH97 | D10: =SIGN(VLOOKUP(target_uk!C10,has_scf!$E$2:$F$1366,2,FALSE)) -> 0 | E10: 43969 | F10: CUST-101588699 | G10: 16087650 | H10: 16033 | K10: Y | N10: Kambi Group Plc | O10: KAMBI | P10: X4170A107 | Q10: MT0000780107 | R10: BMNQDC1 | S10: Rank Group Plc | T10: RNK | U10: G7377H121 | V10: B1L5QH9 | W10: kambi group plc | X10: Rank Group | AI10: 44282
A11: CUSTOMER | B11: =C11&IF(Q11="",W11,Q11) -> GB0031274896LK0080N00008 | C11: GB0031274896 | D11: =SIGN(VLOOKUP(target_uk!C11,has_scf!$E$2:$F$1366,2,FALSE)) -> 1 | E11: 42717 | F11: CUST-101606479 | G11: 22437286 | H11: 1603503 | K11: Y | L11: Hayleys Fabric | N11: Hayleys Plc | O11: HAYL.N0000 | P11: Y3117K102 | Q11: LK0080N00008 | R11: 6416054 | S11: Marks & Spencer Group Plc | T11: MKS | U11: G5824M107 | V11: 3127489 | W11: Hayleys Fabric | X11: Marks & Spencer | Y11: fabric | AI11: 44132
A12: CUSTOMER | B12: =C12&IF(Q12="",W12,Q12) -> GB0031274896LK0080N00008 | C12: GB0031274896 | D12: =SIGN(VLOOKUP(target_uk!C12,has_scf!$E$2:$F$1366,2,FALSE)) -> 1 | E12: 44132 | F12: CUST-101606479 | G12: 22437286 | H12: 1603503 | K12: Y | L12: Hayleys Fabric | N12: Hayleys Plc | O12: HAYL.N0000 | P12: Y3117K102 | Q12: LK0080N00008 | R12: 6416054 | S12: Marks & Spencer Group Plc | T12: MKS | U12: G5824M107 | V12: 3127489 | W12: Hayleys Fabric | X12: Marks & Spencer | Y12: fabric | AI12: 44132
A13: CUSTOMER | B13: =C13&IF(Q13="",W13,Q13) -> GB0032089863LK0080N00008 | C13: GB0032089863 | D13: =SIGN(VLOOKUP(target_uk!C13,has_scf!$E$2:$F$1366,2,FALSE)) -> 0 | E13: 42717 | F13: CUST-101607911 | G13: 22437286 | H13: 1516749 | K13: Y | L13: Hayleys Fabric | N13: Hayleys Plc | O13: HAYL.N0000 | P13: Y3117K102 | Q13: LK0080N00008 | R13: 6416054 | S13: Next Plc | T13: NXT | U13: G6500M106 | V13: 3208986 | W13: Hayleys Fabric | X13: NEXT | Y13: fabric | AI13: 44132
A14: CUSTOMER | B14: =C14&IF(Q14="",W14,Q14) -> GB0032089863LK0080N00008 | C14: GB0032089863 | D14: =SIGN(VLOOKUP(target_uk!C14,has_scf!$E$2:$F$1366,2,FALSE)) -> 0 | E14: 44132 | F14: CUST-101607911 | G14: 22437286 | H14: 1516749 | K14: Y | L14: Hayleys Fabric | N14: Hayleys Plc | O14: HAYL.N0000 | P14: Y3117K102 | Q14: LK0080N00008 | R14: 6416054 | S14: Next Plc | T14: NXT | U14: G6500M106 | V14: 3208986 | W14: Hayleys Fabric | X14: NEXT | Y14: fabric | AI14: 44132
A15: CUSTOMER | B15: =C15&IF(Q15="",W15,Q15) -> GB00B63H8491NO0003064107 | C15: GB00B63H8491 | D15: =SIGN(VLOOKUP(target_uk!C15,has_scf!$E$2:$F$1366,2,FALSE)) -> 1 | E15: 42717 | F15: CUST-101616619 | G15: 194502501 | H15: 240030 | K15: Y | N15: Data Respons AS (Norway) | O15: DAT | P15: R4548G106 | Q15: NO0003064107 | R15: 5195279 | S15: Rolls-Royce Holdings Plc | T15: RR | U15: G76225104 | V15: B63H849 | W15: Data Respons | X15: Rolls-Royce | Y15: global companies | AI15: 44780
A16: CUSTOMER | B16: =C16&IF(Q16="",W16,Q16) -> GB0007325078L. G. Balakrishnan & Brothers | C16: GB0007325078 | D16: =SIGN(VLOOKUP(target_uk!C16,has_scf!$E$2:$F$1366,2,FALSE)) -> 0 | E16: 43379 | F16: CUST-104140497 | G16: 22451503 | H16: 1832454 | K16: Y | M16: Renold Chain India Pvt Ltd | S16: Renold Plc | T16: RNO | U16: G75035108 | V16: 732507 | W16: L. G. Balakrishnan & Brothers | X16: Renold Chain India | AI16: 44140
A17: CUSTOMER | B17: =C17&IF(Q17="",W17,Q17) -> GB0007325078L. G. Balakrishnan & Brothers | C17: GB0007325078 | D17: =SIGN(VLOOKUP(target_uk!C17,has_scf!$E$2:$F$1366,2,FALSE)) -> 0 | E17: 44140 | F17: CUST-104140497 | G17: 22451503 | H17: 1832454 | J17: 0.2 | K17: Y | M17: Renold Chain India Pvt Ltd | S17: Renold Plc | T17: RNO | U17: G75035108 | V17: 732507 | W17: L. G. Balakrishnan & Brothers | X17: Renold Chain India | AI17: 44421
A18: CUSTOMER | B18: =C18&IF(Q18="",W18,Q18) -> GB00BJVH7905Summit Utica | C18: GB00BJVH7905 | D18: =SIGN(VLOOKUP(target_uk!C18,has_scf!$E$2:$F$1366,2,FALSE)) -> 0 | E18: 43542 | F18: CUST-106431549 | G18: 194531900 | H18: 194517589 | K18: Y | L18: Summit Midstream Utica, LLC | M18: Ascent Resources â€“ Utica LLC | N18: Summit Midstream Partners LP | P18: FDS0AL6O1 | S18: Ascent Resources Plc | T18: AST | U18: G05944122 | V18: BJVH790 | W18: Summit Utica | X18: Ascent Resources â€“ Utica LLC | Y18: Utica Shale | AI18: 44319
A19: CUSTOMER | B19: =C19&IF(Q19="",W19,Q19) -> GB0007188757CLP6877L1036 | C19: GB0007188757 | D19: =SIGN(VLOOKUP(target_uk!C19,has_scf!$E$2:$F$1366,2,FALSE)) -> 1 | E19: 43746 | F19: CUST-106477035 | G19: 21070353 | H19: 8792 | K19: Y | M19: Kennecott Molybdenum Company | N19: Molibdenos y Metales SA | O19: MOLYMET | P19: P6877L103 | Q19: CLP6877L1036 | R19: 2543837 | S19: Rio Tinto Plc | T19: RIO | U19: G75754104 | V19: 718875 | W19: Molymet | X19: Kennecott | Y19: Tolling | AI19: 45219
A20: CUSTOMER | B20: =C20&IF(Q20="",W20,Q20) -> GB0033195214TRETRGY00018 | C20: GB0033195214 | D20: =SIGN(VLOOKUP(target_uk!C20,has_scf!$E$2:$F$1366,2,FALSE)) -> 1 | E20: 43566 | F20: CUST-108436577 | G20: 194524064 | H20: 218393 | J20: 1.3 | K20: Y | M20: Koctas Yapi Marketleri Ticaret A.S. | N20: Torunlar Gayrimenkul Yatirim Ortakligi AS | O20: TRGYO.E | P20: M8820E106 | Q20: TRETRGY00018 | R20: B4WW142 | S20: Kingfisher plc | T20: KGF | U20: G5256E441 | V20: 3319521 | W20: Torunlar Gayrimenkul Yatirim Ortakligi | X20: Koctas Yapi Marketleri Ticaret A.S. | Y20: top 10 tenants | AI20: 43973
A21: CUSTOMER | B21: =C21&IF(Q21="",W21,Q21) -> GB0033195214TRETRGY00018 | C21: GB0033195214 | D21: =SIGN(VLOOKUP(target_uk!C21,has_scf!$E$2:$F$1366,2,FALSE)) -> 1 | E21: 43973 | F21: CUST-108436577 | G21: 194524064 | H21: 218393 | J21: 1.3 | K21: Y | M21: Koctas Yapi Marketleri Ticaret A.S. | N21: Torunlar Gayrimenkul Yatirim Ortakligi AS | O21: TRGYO.E | P21: M8820E106 | Q21: TRETRGY00018 | R21: B4WW142 | S21: Kingfisher plc | T21: KGF | U21: G5256E441 | V21: 3319521 | W21: Torunlar Gayrimenkul Yatirim Ortakligi | X21: Koctas Yapi Marketleri Ticaret A.S. | Y21: top 10 tenants | AI21: 43973
A22: CUSTOMER | B22: =C22&IF(Q22="",W22,Q22) -> NL0010545661CNE100000F79 | C22: NL0010545661 | D22: =SIGN(VLOOKUP(target_uk!C22,has_scf!$E$2:$F$1366,2,FALSE)) -> 0 | E22: 43399 | F22: CUST-108718518 | G22: 20706105 | H22: 194536706 | K22: Y | M22: IVECO S.p.A. | N22: Tianrun Industry Technology Co., Ltd. | O22: 2283 | P22: Y8817C102 | Q22: CNE100000F79 | R22: B3YKH94 | S22: CNH Industrial NV | T22: CNH | U22: N20944109 | V22: BDX85Z1 | W22: Tianrun Crankshaft | X22: Iveco | Y22: SAIC-IVECO Commercial Vehicle Investing Co., Ltd. | Z22: crankshaft | AA22: Connecting rods | AB22: Saic Fiat Powertrain Hongyan Co., Ltd. | AI22: 767011
A23: CUSTOMER | B23: =C23&IF(Q23="",W23,Q23) -> GB00B7KR2P84CH0319416936 | C23: GB00B7KR2P84 | D23: =SIGN(VLOOKUP(target_uk!C23,has_scf!$E$2:$F$1366,2,FALSE)) -> 0 | E23: 42872 | F23: CUST-108783614 | G23: 22443919 | H23: 1634656 | K23: Y | N23: Flughafen ZÃ¼rich AG | O23: FHZN | P23: H26552135 | Q23: CH0319416936 | R23: BYQ8481 | S23: easyJet Plc | T23: EZJ | U23: G3030S109 | V23: B7KR2P8 | W23: Flughafen Zuerich | X23: easyJet | Y23: Airlines | AI23: 767011
A24: CUSTOMER | B24: =C24&IF(Q24="",W24,Q24) -> NL0010545661IL0010827348 | C24: NL0010545661 | D24: =SIGN(VLOOKUP(target_uk!C24,has_scf!$E$2:$F$1366,2,FALSE)) -> 0 | E24: 42926 | F24: CUST-110898171 | G24: 249309 | H24: 194536706 | K24: Y | N24: Top Image Systems Ltd. | O24: TISA | P24: M87896102 | Q24: IL0010827348 | R24: 2896520 | S24: CNH Industrial NV | T24: CNH | U24: N20944109 | V24: BDX85Z1 | W24: Top Image Systems | X24: CNH Industrial | Y24: document processing solutions | AI24: 767011
A25: CUSTOMER | B25: =C25&IF(Q25="",W25,Q25) -> GB00B63H8491DE000A2DAM03 | C25: GB00B63H8491 | D25: =SIGN(VLOOKUP(target_uk!C25,has_scf!$E$2:$F$1366,2,FALSE)) -> 1 | E25: 42944 | F25: CUST-111068936 | G25: 103256861 | H25: 240030 | K25: Y | N25: Aumann AG | O25: AAG | P25: D0R9AW106 | Q25: DE000A2DAM03 | R25: BYW82K3 | S25: Rolls-Royce Holdings Plc | T25: RR | U25: G76225104 | V25: B63H849 | W25: aumann ag | X25: Rolls-Royce | Y25: classic | AI25: 44701
A26: CUSTOMER | B26: =C26&IF(Q26="",W26,Q26) -> GB00BMBVGQ36GB00B5N0P849 | C26: GB00BMBVGQ36 | D26: =SIGN(VLOOKUP(target_uk!C26,has_scf!$E$2:$F$1366,2,FALSE)) -> 1 | E26: 42929 | F26: CUST-111076104 | G26: 1587136 | H26: 8264 | K26: Y | N26: John Wood Group Plc | O26: WG | P26: G9745T118 | Q26: GB00B5N0P849 | R26: B5N0P84 | S26: Harbour Energy Plc | T26: HBR | U26: G4289T111 | V26: BMBVGQ3 | W26: John Wood | X26: Premier Oil | Y26: front end engineering design | Z26: topsides | AA26: jacket | AB26: pipeline | AC26: flow assurance | AD26: subsea engineering | AE26: Tolmount offshore field | AF26: Southern North Sea | AI26: 43938
A27: CUSTOMER | B27: =C27&IF(Q27="",W27,Q27) -> GB00BMBVGQ36GB00B5N0P849 | C27: GB00BMBVGQ36 | D27: =SIGN(VLOOKUP(target_uk!C27,has_scf!$E$2:$F$1366,2,FALSE)) -> 1 | E27: 43938 | F27: CUST-111076104 | G27: 1587136 | H27: 8264 | K27: Y | N27: John Wood Group Plc | O27: WG | P27: G9745T118 | Q27: GB00B5N0P849 | R27: B5N0P84 | S27: Harbour Energy Plc | T27: HBR | U27: G4289T111 | V27: BMBVGQ3 | W27: John Wood | X27: Premier Oil | Y27: front end engineering design | Z27: topsides | AA27: jacket | AB27: pipeline | AC27: flow assurance | AD27: subsea engineering | AE27: Tolmount offshore field | AF27: Southern North Sea | AI27: 43938
A28: CUSTOMER | B28: =C28&IF(Q28="",W28,Q28) -> GB0005603997AU000000BVS9 | C28: GB0005603997 | D28: =SIGN(VLOOKUP(target_uk!C28,has_scf!$E$2:$F$1366,2,FALSE)) -> 0 | E28: 42929 | F28: CUST-111136388 | G28: 22246309 | H28: 1402018 | K28: Y | N28: Bravura Solutions Ltd. | O28: BVS | P28: Q17548167 | Q28: AU000000BVS9 | R28: BZBHBM3 | S28: Legal & General Group Plc | T28: LGEN | U28: G54404127 | V28: 560399 | W28: Bravura Solutions | X28: Legal & General | Y28: financial solutions | AI28: 44780
A29: CUSTOMER | B29: =C29&IF(Q29="",W29,Q29) -> GB00BP9LHF23AU000000BVS9 | C29: GB00BP9LHF23 | D29: =SIGN(VLOOKUP(target_uk!C29,has_scf!$E$2:$F$1366,2,FALSE)) -> 0 | E29: 42929 | F29: CUST-111136426 | G29: 22246309 | H29: 1732173 | K29: Y | N29: Bravura Solutions Ltd. | O29: BVS | P29: Q17548167 | Q29: AU000000BVS9 | R29: BZBHBM3 | S29: Schroders Plc | T29: SDR | U29: G78602144 | V29: BP9LHF2 | W29: Bravura Solutions | X29: Schroders | Y29: financial solutions | AI29: 45168
A30: CUSTOMER | B30: =C30&IF(Q30="",W30,Q30) -> GB00B63H8491US0048482063 | C30: GB00B63H8491 | D30: =SIGN(VLOOKUP(target_uk!C30,has_scf!$E$2:$F$1366,2,FALSE)) -> 1 | E30: 42930 | F30: CUST-111170190 | G30: 3001 | H30: 240030 | K30: Y | L30: OmniMetrix, LLC | M30: MTU Onsite Energy | N30: Acorn Energy, Inc. | O30: ACFN | P30: 4848206 | Q30: US0048482063 | R30: BQBBF53 | S30: Rolls-Royce Holdings Plc | T30: RR | U30: G76225104 | V30: B63H849 | W30: OmniMetrix | X30: MTU Solutions | Y30: PG monitors | AI30: 43943
A31: CUSTOMER | B31: =C31&IF(Q31="",W31,Q31) -> GB00B63H8491US0048482063 | C31: GB00B63H8491 | D31: =SIGN(VLOOKUP(target_uk!C31,has_scf!$E$2:$F$1366,2,FALSE)) -> 1 | E31: 43943 | F31: CUST-111170190 | G31: 3001 | H31: 240030 | K31: Y | L31: OmniMetrix, LLC | M31: MTU Energy | N31: Acorn Energy, Inc. | O31: ACFN | P31: 4848206 | Q31: US0048482063 | R31: BQBBF53 | S31: Rolls-Royce Holdings Plc | T31: RR | U31: G76225104 | V31: B63H849 | W31: OmniMetrix | X31: MTU Solutions | Y31: PG monitors | AI31: 44780
A32: CUSTOMER | B32: =C32&IF(Q32="",W32,Q32) -> GB0033195214US0296831094 | C32: GB0033195214 | D32: =SIGN(VLOOKUP(target_uk!C32,has_scf!$E$2:$F$1366,2,FALSE)) -> 1 | E32: 42984 | F32: CUST-113126290 | G32: 611 | H32: 218393 | K32: Y | M32: Screwfix Direct Ltd. | N32: Logility Supply Chain Solutions, Inc. | O32: LGTY | P32: 29683109 | Q32: US0296831094 | R32: 2029575 | S32: Kingfisher plc | T32: KGF | U32: G5256E441 | V32: 3319521 | W32: American Software | X32: Screwfix | Y32: Software Solutions | Z32: Wholesale distribution | AI32: 767011
A33: CUSTOMER | B33: =C33&IF(Q33="",W33,Q33) -> GB0006215205US2506601077 | C33: GB0006215205 | D33: =SIGN(VLOOKUP(target_uk!C33,has_scf!$E$2:$F$1366,2,FALSE)) -> 1 | E33: 42984 | F33: CUST-113164239 | G33: 80724223 | H33: 1606358 | K33: Y | M33: c2c Rail Ltd. | N33: Determine, Inc. | O33: DTRM | P33: 250660107 | Q33: US2506601077 | R33: BYNK9L8 | S33: Mobico Group Plc | T33: MCG | U33: G6374M109 | V33: 621520 | W33: Determine | X33: c2c | Y33: Determine Cloud Platform | AI33: 43836
A34: CUSTOMER | B34: =C34&IF(Q34="",W34,Q34) -> GB0006215205US2506601077 | C34: GB0006215205 | D34: =SIGN(VLOOKUP(target_uk!C34,has_scf!$E$2:$F$1366,2,FALSE)) -> 1 | E34: 43836 | F34: CUST-113164239 | G34: 80724223 | H34: 1606358 | K34: Y | M34: c2c Rail Ltd. | N34: Determine, Inc. | O34: DTRM | P34: 250660107 | Q34: US2506601077 | R34: BYNK9L8 | S34: Mobico Group Plc | T34: MCG | U34: G6374M109 | V34: 621520 | W34: Determine | X34: c2c | Y34: Determine Cloud Platform | AI34: 43836
A35: CUSTOMER | B35: =C35&IF(Q35="",W35,Q35) -> GB00BNLPYF73US24661P8077 | C35: GB00BNLPYF73 | D35: =SIGN(VLOOKUP(target_uk!C35,has_scf!$E$2:$F$1366,2,FALSE)) -> 0 | E35: 42984 | F35: CUST-113177424 | G35: 248227 | H35: 63440346 | K35: Y | M35: Spire Southampton Hospital | N35: Delcath Systems, Inc. | O35: DCTH | P35: 24661P807 | Q35: US24661P8077 | R35: BK228T8 | S35: Spire Healthcare Group Plc | T35: SPI | U35: G83577109 | V35: BNLPYF7 | W35: Delcath Systems | X35: Spire Southampton Hospital | Y35: percutaneous hepatic perfusion | Z35: PHP | AA35: CHEMOSTAT | AB35: Melphalan/HDS | AC35: whole organ therapy | AD35: liver | AE35: Europe | AI35: 43872
A36: CUSTOMER | B36: =C36&IF(Q36="",W36,Q36) -> GB00BNLPYF73US24661P8077 | C36: GB00BNLPYF73 | D36: =SIGN(VLOOKUP(target_uk!C36,has_scf!$E$2:$F$1366,2,FALSE)) -> 0 | E36: 43872 | F36: CUST-113177424 | G36: 248227 | H36: 63440346 | K36: Y | M36: Spire Southampton Hospital | N36: Delcath Systems, Inc. | O36: DCTH | P36: 24661P807 | Q36: US24661P8077 | R36: BK228T8 | S36: Spire Healthcare Group Plc | T36: SPI | U36: G83577109 | V36: BNLPYF7 | W36: Delcath Systems | X36: Spire Southampton Hospital | Y36: percutaneous hepatic perfusion | Z36: PHP | AA36: CHEMOSTAT | AB36: Melphalan/HDS | AC36: whole organ therapy | AD36: liver | AE36: Europe | AI36: 43872
A37: CUSTOMER | B37: =C37&IF(Q37="",W37,Q37) -> GB00BMWC6P49AT000AGRANA3 | C37: GB00BMWC6P49 | D37: =SIGN(VLOOKUP(target_uk!C37,has_scf!$E$2:$F$1366,2,FALSE)) -> 0 | E37: 42986 | F37: CUST-113263455 | G37: 194502681 | H37: 1921554 | K37: Y | N37: AGRANA Beteiligungs-AG | O37: AGR | P37: A0091P145 | Q37: AT000AGRANA3 | R37: BF0X9L7 | S37: Mondi Plc | T37: MNDI | U37: G6258S115 | V37: BMWC6P4 | W37: Agrana Beteiligungs | X37: Mondi | AI37: 45068
A38: CUSTOMER | B38: =C38&IF(Q38="",W38,Q38) -> GB00B63H8491EE3100004250 | C38: GB00B63H8491 | D38: =SIGN(VLOOKUP(target_uk!C38,has_scf!$E$2:$F$1366,2,FALSE)) -> 1 | E38: 42991 | F38: CUST-113368073 | G38: 194503576 | H38: 240030 | K38: Y | N38: Harju Elekter Group AS | O38: HAE1T | P38: X3244C107 | Q38: EE3100004250 | R38: 5392070 | S38: Rolls-Royce Holdings Plc | T38: RR | U38: G76225104 | V38: B63H849 | W38: Harju Elekter | X38: Rolls-Royce | Y38: clients | AI38: 44110
A39: CUSTOMER | B39: =C39&IF(Q39="",W39,Q39) -> GB00B63H8491EE3100004250 | C39: GB00B63H8491 | D39: =SIGN(VLOOKUP(target_uk!C39,has_scf!$E$2:$F$1366,2,FALSE)) -> 1 | E39: 44110 | F39: CUST-113368073 | G39: 194503576 | H39: 240030 | K39: Y | N39: Harju Elekter Group AS | O39: HAE1T | P39: X3244C107 | Q39: EE3100004250 | R39: 5392070 | S39: Rolls-Royce Holdings Plc | T39: RR | U39: G76225104 | V39: B63H849 | W39: Harju Elekter | X39: Rolls-Royce | Y39: clients | AI39: 44110
A40: CUSTOMER | B40: =C40&IF(Q40="",W40,Q40) -> GB00B60BWY28FR0000064446 | C40: GB00B60BWY28 | D40: =SIGN(VLOOKUP(target_uk!C40,has_scf!$E$2:$F$1366,2,FALSE)) -> 0 | E40: 43033 | F40: CUST-115202677 | G40: 1922749 | H40: 194524051 | K40: Y | N40: Catering International & Services | O40: ALCIS | P40: F1422H104 | Q40: FR0000064446 | R40: 7172946 | S40: Hummingbird Resources Plc | T40: HUM | U40: G4706Q104 | V40: B60BWY2 | W40: Catering International | X40: Hummingbird | AI40: 44391
A41: CUSTOMER | B41: =C41&IF(Q41="",W41,Q41) -> GB0031274896PLINTEG00011 | C41: GB0031274896 | D41: =SIGN(VLOOKUP(target_uk!C41,has_scf!$E$2:$F$1366,2,FALSE)) -> 1 | E41: 43034 | F41: CUST-115284795 | G41: 22448698 | H41: 1603503 | K41: Y | N41: Integer.pl SA | O41: ITG | P41: X3959Z101 | Q41: PLINTEG00011 | R41: B28XF21 | S41: Marks & Spencer Group Plc | T41: MKS | U41: G5824M107 | V41: 3127489 | W41: Integer | X41: Marks & Spencer | AI41: 767011
A42: CUSTOMER | B42: =C42&IF(Q42="",W42,Q42) -> GB00BM8Q5M07PLINTEG00011 | C42: GB00BM8Q5M07 | D42: =SIGN(VLOOKUP(target_uk!C42,has_scf!$E$2:$F$1366,2,FALSE)) -> 0 | E42: 43034 | F42: CUST-115286317 | G42: 22448698 | H42: 1832342 | K42: Y | M42: Go Outdoors Ltd | N42: Integer.pl SA | O42: ITG | P42: X3959Z101 | Q42: PLINTEG00011 | R42: B28XF21 | S42: JD Sports Fashion Plc | T42: JD | U42: G5144Y120 | V42: BM8Q5M0 | W42: Integer | X42: JD Sports Fashion | Y42: Go Outdoors | Z42: United Kingdom | AI42: 767011
A43: CUSTOMER | B43: =C43&IF(Q43="",W43,Q43) -> GB00BD8QVC95PLINTEG00011 | C43: GB00BD8QVC95 | D43: =SIGN(VLOOKUP(target_uk!C43,has_scf!$E$2:$F$1366,2,FALSE)) -> 0 | E43: 43034 | F43: CUST-115287765 | G43: 22448698 | H43: 67162028 | K43: Y | M43: iForce Group Ltd | N43: Integer.pl SA | O43: ITG | P43: X3959Z101 | Q43: PLINTEG00011 | R43: B28XF21 | S43: Logistics Development Group Plc | T43: LDG | U43: G5557U102 | V43: BD8QVC9 | W43: Integer | X43: Eddie Stobart Logistics | Y43: iForce | Z43: United Kingdom | AI43: 767011
A44: CUSTOMER | B44: =C44&IF(Q44="",W44,Q44) -> GB00B24CGK77FR0010929125 | C44: GB00B24CGK77 | D44: =SIGN(VLOOKUP(target_uk!C44,has_scf!$E$2:$F$1366,2,FALSE)) -> 1 | E44: 43035 | F44: CUST-115322242 | G44: 194530758 | H44: 1530394 | K44: Y | N44: ID Logistics Group | O44: IDL | P44: F50685100 | Q44: FR0010929125 | R44: B4RFDT5 | S44: Reckitt Benckiser Group Plc | T44: RKT | U44: G74079107 | V44: B24CGK7 | W44: ID Logistics | X44: Reckitt Benckiser Group | Y44: healthcare | AI44: 767011
A45: CUSTOMER | B45: =C45&IF(Q45="",W45,Q45) -> GB0033195214FR0010929125 | C45: GB0033195214 | D45: =SIGN(VLOOKUP(target_uk!C45,has_scf!$E$2:$F$1366,2,FALSE)) -> 1 | E45: 43035 | F45: CUST-115324228 | G45: 194530758 | H45: 218393 | K45: Y | M45: Castorama France SAS | N45: ID Logistics Group | O45: IDL | P45: F50685100 | Q45: FR0010929125 | R45: B4RFDT5 | S45: Kingfisher plc | T45: KGF | U45: G5256E441 | V45: 3319521 | W45: ID Logistics | X45: Castorama France | Y45: non-food retail | AI45: 767011
A46: CUSTOMER | B46: =C46&IF(Q46="",W46,Q46) -> GB00B7KR2P84GB00BD736828 | C46: GB00B7KR2P84 | D46: =SIGN(VLOOKUP(target_uk!C46,has_scf!$E$2:$F$1366,2,FALSE)) -> 0 | E46: 43699 | F46: CUST-115340015 | G46: 1832137 | H46: 1634656 | K46: Y | L46: Baines Simmons Ltd. | N46: Air Partner Ltd. | O46: AIR | P46: G01358111 | Q46: GB00BD736828 | R46: BD73682 | S46: easyJet Plc | T46: EZJ | U46: G3030S109 | V46: B7KR2P8 | W46: Baines Simmons | X46: easyJet | Y46: Civil Aviation | AI46: 45212
A47: CUSTOMER | B47: =C47&IF(Q47="",W47,Q47) -> GB00B71N6K86MXP0598H1110 | C47: GB00B71N6K86 | D47: =SIGN(VLOOKUP(target_uk!C47,has_scf!$E$2:$F$1366,2,FALSE)) -> 0 | E47: 43054 | F47: CUST-115366143 | G47: 20968543 | H47: 194529527 | K47: Y | M47: EVRAZ Rocky Mountain Steel | N47: CompaÃ±ia Minera Autlan SA de CV | O47: AUTLANB | P47: P0598H111 | Q47: MXP0598H1110 | R47: 2176976 | S47: EVRAZ Plc | T47: EVR | U47: G33090104 | V47: B71N6K8 | W47: Autlan | X47: EVRAZ Rocky Mountain Steel | Y47: manganese ferroalloys | AI47: 44457
A48: CUSTOMER | B48: =C48&IF(Q48="",W48,Q48) -> GB0030927254GB00BVMTNR93 | C48: GB0030927254 | D48: =SIGN(VLOOKUP(target_uk!C48,has_scf!$E$2:$F$1366,2,FALSE)) -> 0 | E48: 43669 | F48: CUST-115518159 | G48: 1832422 | H48: 194517741 | K48: Y | N48: PayPoint Plc | O48: PAY | P48: G6953A104 | Q48: GB00BVMTNR93 | R48: BVMTNR9 | S48: ASOS Plc | T48: ASC | U48: G0536Q108 | V48: 3092725 | W48: Paypoint | X48: ASOS | AI48: 44425
A49: CUSTOMER | B49: =C49&IF(Q49="",W49,Q49) -> GB00BD6GN030Monitise | C49: GB00BD6GN030 | D49: =SIGN(VLOOKUP(target_uk!C49,has_scf!$E$2:$F$1366,2,FALSE)) -> 0 | E49: 42690 | F49: CUST-100561697 | G49: 194516600 | H49: 81080036 | K49: Y | M49: Clydesdale Bank plc | S49: Virgin Money UK Plc | T49: VMUK | U49: G9413V106 | V49: BD6GN03 | W49: Monitise | X49: Clydesdale Bank | Y49: Banking Solutions | AI49: 44817
A50: CUSTOMER | B50: =C50&IF(Q50="",W50,Q50) -> GB0002875804SGXE13591867 | C50: GB0002875804 | D50: =SIGN(VLOOKUP(target_uk!C50,has_scf!$E$2:$F$1366,2,FALSE)) -> 1 | E50: 43673 | F50: CUST-100588813 | G50: 6261984 | H50: 1718327 | K50: Y | L50: Noon Pictures Co., Ltd. | N50: Spackman Entertainment Group Ltd. | O50: 9VW | P50: Y8089Y113 | Q50: SGXE13591867 | R50: BV4MHR4 | S50: British American Tobacco plc | T50: BATS | U50: G1510J102 | V50: 287580 | W50: Spackman Entertainment Group | X50: British American Tobacco | AI50: 45422
A51: CUSTOMER | B51: =C51&IF(Q51="",W51,Q51) -> GB0007188757NZHBYE0001S8 | C51: GB0007188757 | D51: =SIGN(VLOOKUP(target_uk!C51,has_scf!$E$2:$F$1366,2,FALSE)) -> 1 | E51: 42692 | F51: CUST-100650658 | G51: 194504443 | H51: 8792 | K51: Y | L51: Contract Resources Investments Limited | N51: Bapcor New Zealand Ltd. | O51: HBY | P51: Q4568F112 | Q51: NZHBYE0001S8 | R51: 6414694 | S51: Rio Tinto Plc | T51: RIO | U51: G75754104 | V51: 718875 | W51: Contract Resources Investments Limited | X51: Rio Tinto | Y51: Resources Services | Z51: industrial and mechanical services | AI51: 45405
A52: CUSTOMER | B52: =C52&IF(Q52="",W52,Q52) -> GB00B24CGK77PK0064301010 | C52: GB00B24CGK77 | D52: =SIGN(VLOOKUP(target_uk!C52,has_scf!$E$2:$F$1366,2,FALSE)) -> 1 | E52: 42692 | F52: CUST-100655090 | G52: 194501298 | H52: 1530394 | K52: Y | N52: Ghani Glass Ltd. | O52: GHGL | P52: Y2708N103 | Q52: PK0064301010 | R52: 6373308 | S52: Reckitt Benckiser Group Plc | T52: RKT | U52: G74079107 | V52: B24CGK7 | W52: ghani glass | X52: Reckitt Benckiser Group | Y52: pharmaceutical glass containers | AI52: 44482
A53: CUSTOMER | B53: =C53&IF(Q53="",W53,Q53) -> GB00B1CKQ739GB0004254875 | C53: GB00B1CKQ739 | D53: =SIGN(VLOOKUP(target_uk!C53,has_scf!$E$2:$F$1366,2,FALSE)) -> 0 | E53: 43327 | F53: CUST-100759850 | G53: 1832296 | H53: 1832242 | K53: Y | N53: Highcroft Investments Plc | O53: HCFT | P53: G44492117 | Q53: GB0004254875 | R53: 425487 | S53: Dunelm Group Plc | T53: DNLM | U53: G2935W108 | V53: B1CKQ73 | W53: Highcroft | X53: Dunelm | Y53: Wisbech | Z53: tenant | AI53: 767011
A54: CUSTOMER | B54: =C54&IF(Q54="",W54,Q54) -> GB00BK9RKT01GB0004254875 | C54: GB00BK9RKT01 | D54: =SIGN(VLOOKUP(target_uk!C54,has_scf!$E$2:$F$1366,2,FALSE)) -> 1 | E54: 42696 | F54: CUST-100761126 | G54: 1832296 | H54: 1776804 | K54: Y | M54: Wickes | N54: Highcroft Investments Plc | O54: HCFT | P54: G44492117 | Q54: GB0004254875 | R54: 425487 | S54: Travis Perkins Plc | T54: TPK | U54: G90202139 | V54: BK9RKT0 | W54: Highcroft | X54: Travis Perkins | Y54: let to | Z54: Retail warehouse in Bicester | AA54: tenant | AI54: 44361
A55: CUSTOMER | B55: =C55&IF(Q55="",W55,Q55) -> GB00BJ3VW957IE000Y2HN3O9 | C55: GB00BJ3VW957 | D55: =SIGN(VLOOKUP(target_uk!C55,has_scf!$E$2:$F$1366,2,FALSE)) -> 1 | E55: 43255 | F55: CUST-103251317 | G55: 194522008 | H55: 59558316 | K55: Y | L55: Nomadic Dairy | N55: Donegal Investment Group Plc | O55: DQ7A | P55: G28153156 | Q55: IE000Y2HN3O9 | R55: BS2J1G3 | S55: McColl's Retail Group Plc | T55: MCLS | U55: G59531106 | V55: BJ3VW95 | W55: Nomadic Dairy | X55: Mccolls | AI55: 43960
A56: CUSTOMER | B56: =C56&IF(Q56="",W56,Q56) -> GB00BJ3VW957IE000Y2HN3O9 | C56: GB00BJ3VW957 | D56: =SIGN(VLOOKUP(target_uk!C56,has_scf!$E$2:$F$1366,2,FALSE)) -> 1 | E56: 43960 | F56: CUST-103251317 | G56: 194522008 | H56: 59558316 | K56: Y | L56: Nomadic Dairy Ltd | N56: Donegal Investment Group Plc | O56: DQ7A | P56: G28153156 | Q56: IE000Y2HN3O9 | R56: BS2J1G3 | S56: McColl's Retail Group Plc | T56: MCLS | U56: G59531106 | V56: BJ3VW95 | W56: Nomadic Dairy | X56: Mccolls | AI56: 45149
A57: CUSTOMER | B57: =C57&IF(Q57="",W57,Q57) -> GB0002875804GB00BMMV6B79 | C57: GB0002875804 | D57: =SIGN(VLOOKUP(target_uk!C57,has_scf!$E$2:$F$1366,2,FALSE)) -> 1 | E57: 42755 | F57: CUST-103416815 | G57: 16068911 | H57: 1718327 | K57: Y | N57: GXO Logistics UK II Ltd. | O57: CLG | P57: G2203Y109 | Q57: GB00BMMV6B79 | R57: BMMV6B7 | S57: British American Tobacco plc | T57: BATS | U57: G1510J102 | V57: 287580 | W57: Clipper Logistics | X57: British American Tobacco | AI57: 45212
A58: CUSTOMER | B58: =C58&IF(Q58="",W58,Q58) -> GB00B012TP20GB00BMMV6B79 | C58: GB00B012TP20 | D58: =SIGN(VLOOKUP(target_uk!C58,has_scf!$E$2:$F$1366,2,FALSE)) -> 0 | E58: 43088 | F58: CUST-103540908 | G58: 16068911 | H58: 1832300 | K58: Y | M58: Halfords Ltd | N58: GXO Logistics UK II Ltd. | O58: CLG | P58: G2203Y109 | Q58: GB00BMMV6B79 | R58: BMMV6B7 | S58: Halfords Group Plc | T58: HFD | U58: G4280E105 | V58: B012TP2 | W58: Clipper Logistics | X58: Halfords | AI58: 45215
A59: CUSTOMER | B59: =C59&IF(Q59="",W59,Q59) -> GB00BM8Q5M07GB00BMMV6B79 | C59: GB00BM8Q5M07 | D59: =SIGN(VLOOKUP(target_uk!C59,has_scf!$E$2:$F$1366,2,FALSE)) -> 0 | E59: 42759 | F59: CUST-103550048 | G59: 16068911 | H59: 1832342 | K59: Y | M59: Go Outdoors Ltd | N59: GXO Logistics UK II Ltd. | O59: CLG | P59: G2203Y109 | Q59: GB00BMMV6B79 | R59: BMMV6B7 | S59: JD Sports Fashion Plc | T59: JD | U59: G5144Y120 | V59: BM8Q5M0 | W59: Clipper Logistics | X59: Go Outdoors | AI59: 44070
A60: CUSTOMER | B60: =C60&IF(Q60="",W60,Q60) -> GB00BM8Q5M07GB00BMMV6B79 | C60: GB00BM8Q5M07 | D60: =SIGN(VLOOKUP(target_uk!C60,has_scf!$E$2:$F$1366,2,FALSE)) -> 0 | E60: 44070 | F60: CUST-103550048 | G60: 16068911 | H60: 1832342 | K60: Y | M60: Go Outdoors Ltd | N60: GXO Logistics UK II Ltd. | O60: CLG | P60: G2203Y109 | Q60: GB00BMMV6B79 | R60: BMMV6B7 | S60: JD Sports Fashion Plc | T60: JD | U60: G5144Y120 | V60: BM8Q5M0 | W60: Clipper Logistics | X60: Go Outdoors | AI60: 44070
A61: CUSTOMER | B61: =C61&IF(Q61="",W61,Q61) -> GB0004544929GB00BMMV6B79 | C61: GB0004544929 | D61: =SIGN(VLOOKUP(target_uk!C61,has_scf!$E$2:$F$1366,2,FALSE)) -> 0 | E61: 43399 | F61: CUST-103550922 | G61: 16068911 | H61: 219068 | K61: Y | M61: Imperial Tobacco | N61: GXO Logistics UK II Ltd. | O61: CLG | P61: G2203Y109 | Q61: GB00BMMV6B79 | R61: BMMV6B7 | S61: Imperial Brands Plc | T61: IMB | U61: G4720C107 | V61: 454492 | W61: Clipper Logistics | X61: Imperial Tobacco | AI61: 44070
A62: CUSTOMER | B62: =C62&IF(Q62="",W62,Q62) -> GB0004544929GB00BMMV6B79 | C62: GB0004544929 | D62: =SIGN(VLOOKUP(target_uk!C62,has_scf!$E$2:$F$1366,2,FALSE)) -> 0 | E62: 44070 | F62: CUST-103550922 | G62: 16068911 | H62: 219068 | K62: Y | M62: Imperial Tobacco Ltd | N62: GXO Logistics UK II Ltd. | O62: CLG | P62: G2203Y109 | Q62: GB00BMMV6B79 | R62: BMMV6B7 | S62: Imperial Brands Plc | T62: IMB | U62: G4720C107 | V62: 454492 | W62: Clipper Logistics | X62: Imperial Tobacco | AI62: 45215
A63: CUSTOMER | B63: =C63&IF(Q63="",W63,Q63) -> GB00B7KR2P84IT0005176406 | C63: GB00B7KR2P84 | D63: =SIGN(VLOOKUP(target_uk!C63,has_scf!$E$2:$F$1366,2,FALSE)) -> 0 | E63: 43070 | F63: CUST-103570689 | G63: 8012643 | H63: 1634656 | K63: Y | N63: ENAV SpA | O63: ENAV | P63: T3R4KN103 | Q63: IT0005176406 | R63: BD0CRV6 | S63: easyJet Plc | T63: EZJ | U63: G3030S109 | V63: B7KR2P8 | W63: enav spa | X63: easyJet | AI63: 767011
A64: CUSTOMER | B64: =C64&IF(Q64="",W64,Q64) -> GB00B03HDJ73US16942X3026 | C64: GB00B03HDJ73 | D64: =SIGN(VLOOKUP(target_uk!C64,has_scf!$E$2:$F$1366,2,FALSE)) -> 0 | E64: 42760 | F64: CUST-103635882 | G64: 1850822 | H64: 1921534 | K64: Y | N64: China Sunergy Co., Ltd. | O64: CSUNY | P64: 16942X302 | Q64: US16942X3026 | R64: B75M2H0 | S64: Esken Ltd. | T64: ESKN | U64: G3124P102 | V64: B03HDJ7 | W64: Sunergy | X64: Stobart Group | Y64: London Southend Airport | Z64: solar farm | AA64: solar modules | AI64: 45405
A65: CUSTOMER | B65: =C65&IF(Q65="",W65,Q65) -> GB00B71N6K86US4158641070 | C65: GB00B71N6K86 | D65: =SIGN(VLOOKUP(target_uk!C65,has_scf!$E$2:$F$1366,2,FALSE)) -> 0 | E65: 42801 | F65: CUST-105531525 | G65: 4832 | H65: 194529527 | K65: Y | N65: Enviri Corp. | O65: NVRI | P65: 415864107 | Q65: US4158641070 | R65: 2412700 | S65: EVRAZ Plc | T65: EVR | U65: G33090104 | V65: B71N6K8 | W65: Harsco | X65: EVRAZ | Y65: scrap management services | AI65: 44620
A66: CUSTOMER | B66: =C66&IF(Q66="",W66,Q66) -> GB0031638363US14862Q1004 | C66: GB0031638363 | D66: =SIGN(VLOOKUP(target_uk!C66,has_scf!$E$2:$F$1366,2,FALSE)) -> 0 | E66: 42802 | F66: CUST-105557750 | G66: 7512606 | H66: 1799343 | K66: Y | N66: Castlight Health, Inc. | O66: CSLT | P66: 14862Q100 | Q66: US14862Q1004 | R66: BKF2K11 | S66: Intertek Group Plc | T66: ITRK | U66: G4911B108 | V66: 3163836 | W66: Castlight Health | X66: Intertek Group | Y66: health benefits platform | AI66: 43896
A67: CUSTOMER | B67: =C67&IF(Q67="",W67,Q67) -> GB0031638363US14862Q1004 | C67: GB0031638363 | D67: =SIGN(VLOOKUP(target_uk!C67,has_scf!$E$2:$F$1366,2,FALSE)) -> 0 | E67: 43896 | F67: CUST-105557750 | G67: 7512606 | H67: 1799343 | K67: Y | N67: Castlight Health, Inc. | O67: CSLT | P67: 14862Q100 | Q67: US14862Q1004 | R67: BKF2K11 | S67: Intertek Group Plc | T67: ITRK | U67: G4911B108 | V67: 3163836 | W67: Castlight Health | X67: Intertek Group | Y67: health benefits platform | AI67: 43896
A68: CUSTOMER | B68: =C68&IF(Q68="",W68,Q68) -> GB00B1722W11US09238E1047 | C68: GB00B1722W11 | D68: =SIGN(VLOOKUP(target_uk!C68,has_scf!$E$2:$F$1366,2,FALSE)) -> 0 | E68: 42807 | F68: CUST-105840081 | G68: 194535512 | H68: 194508808 | K68: Y | N68: Blackhawk Network Holdings, Inc. | O68: HAWK | P68: 9.238e+107 | Q68: US09238E1047 | R68: B9GPVY2 | S68: Jet2 Plc | T68: JET2 | U68: G5112P101 | V68: B1722W1 | W68: Blackhawk Network | X68: Dart Group | Y68: Closed Loop (Private-Branded) Gift Cards | AI68: 767011
A69: CUSTOMER | B69: =C69&IF(Q69="",W69,Q69) -> GB0007188757CA80013R2063 | C69: GB0007188757 | D69: =SIGN(VLOOKUP(target_uk!C69,has_scf!$E$2:$F$1366,2,FALSE)) -> 1 | E69: 42858 | F69: CUST-107837581 | G69: 194513849 | H69: 8792 | K69: Y | M69: Diavik Diamond Mines Inc | N69: Sandstorm Gold Ltd. | O69: SSL | P69: 80013R206 | Q69: CA80013R2063 | R69: B7YC668 | S69: Rio Tinto Plc | T69: RIO | U69: G75754104 | V69: 718875 | W69: Sandstorm Gold | X69: Rio Tinto | Y69: Diavik Mine | Z69: Diamonds | AA69: royalty | AB69: Copper Cliff | AI69: 44321
A70: CUSTOMER | B70: =C70&IF(Q70="",W70,Q70) -> GB00B63H8491FR0000073272 | C70: GB00B63H8491 | D70: =SIGN(VLOOKUP(target_uk!C70,has_scf!$E$2:$F$1366,2,FALSE)) -> 1 | E70: 42857 | F70: CUST-107997773 | G70: 1923203 | H70: 240030 | K70: Y | N70: Safran SA | O70: SAF | P70: F4035A557 | Q70: FR0000073272 | R70: B058TZ6 | S70: Rolls-Royce Holdings Plc | T70: RR | U70: G76225104 | V70: B63H849 | W70: SAFRAN | X70: Rolls-Royce | Y70: Mechanical power transmission systems | AI70: 44780
A71: CUSTOMER | B71: =C71&IF(Q71="",W71,Q71) -> GB00B7KR2P84GB00BYWWHR75 | C71: GB00B7KR2P84 | D71: =SIGN(VLOOKUP(target_uk!C71,has_scf!$E$2:$F$1366,2,FALSE)) -> 0 | E71: 42904 | F71: CUST-110026774 | G71: 8835835 | H71: 1634656 | K71: Y | N71: Equiniti Group Ltd. | O71: EQN | P71: G315B4104 | Q71: GB00BYWWHR75 | R71: BYWWHR7 | S71: easyJet Plc | T71: EZJ | U71: G3030S109 | V71: B7KR2P8 | W71: EQUINITI GROUP | X71: easyJet | Y71: financial solutions | AI71: 45723
A72: CUSTOMER | B72: =C72&IF(Q72="",W72,Q72) -> GB00BMX64W89GB00BYWWHR75 | C72: GB00BMX64W89 | D72: =SIGN(VLOOKUP(target_uk!C72,has_scf!$E$2:$F$1366,2,FALSE)) -> 0 | E72: 42904 | F72: CUST-110027272 | G72: 8835835 | H72: 6788916 | K72: Y | N72: Equiniti Group Ltd. | O72: EQN | P72: G315B4104 | Q72: GB00BYWWHR75 | R72: BYWWHR7 | S72: Saga Plc | T72: SAGA | U72: G7770H124 | V72: BMX64W8 | W72: EQUINITI GROUP | X72: Saga plc | Y72: financial solutions | AI72: 43979
A73: CUSTOMER | B73: =C73&IF(Q73="",W73,Q73) -> GB00BMX64W89GB00BYWWHR75 | C73: GB00BMX64W89 | D73: =SIGN(VLOOKUP(target_uk!C73,has_scf!$E$2:$F$1366,2,FALSE)) -> 0 | E73: 43979 | F73: CUST-110027272 | G73: 8835835 | H73: 6788916 | K73: Y | N73: Equiniti Group Ltd. | O73: EQN | P73: G315B4104 | Q73: GB00BYWWHR75 | R73: BYWWHR7 | S73: Saga Plc | T73: SAGA | U73: G7770H124 | V73: BMX64W8 | W73: EQUINITI GROUP | X73: Saga plc | Y73: financial solutions | AI73: 43979
A74: CUSTOMER | B74: =C74&IF(Q74="",W74,Q74) -> JE00B8KF9B49US88339J1051 | C74: JE00B8KF9B49 | D74: =SIGN(VLOOKUP(target_uk!C74,has_scf!$E$2:$F$1366,2,FALSE)) -> 0 | E74: 42905 | F74: CUST-110076112 | G74: 8771626 | H74: 11232 | K74: Y | N74: The Trade Desk, Inc. | O74: TTD | P74: 88339J105 | Q74: US88339J1051 | R74: BD8FDD1 | S74: WPP Plc | T74: WPP | U74: G9788D103 | V74: B8KF9B4 | W74: Trade Desk | X74: WPP | Y74: Advertising Solutions | AI74: 45343
A75: CUSTOMER | B75: =C75&IF(Q75="",W75,Q75) -> GB00B24CGK77MYL5908OO008 | C75: GB00B24CGK77 | D75: =SIGN(VLOOKUP(target_uk!C75,has_scf!$E$2:$F$1366,2,FALSE)) -> 1 | E75: 43061 | F75: CUST-110159343 | G75: 194505803 | H75: 1530394 | K75: Y | M75: Mead Johnson Nutrition Company | N75: DKSH Holdings (Malaysia) Bhd. | O75: 5908 | P75: Y2104N103 | Q75: MYL5908OO008 | R75: 6253176 | S75: Reckitt Benckiser Group Plc | T75: RKT | U75: G74079107 | V75: B24CGK7 | W75: DKSH | X75: Mead Johnson | Y75: consumer goods, enfagrow | AI75: 45180
A76: CUSTOMER | B76: =C76&IF(Q76="",W76,Q76) -> GB00B24CGK77CNE100000LV8 | C76: GB00B24CGK77 | D76: =SIGN(VLOOKUP(target_uk!C76,has_scf!$E$2:$F$1366,2,FALSE)) -> 1 | E76: 42906 | F76: CUST-110159349 | G76: 194513273 | H76: 1530394 | K76: Y | M76: JOHNSON MEAD NUTRITION CO | N76: BlueFocus Intelligent Communications Group Co. Ltd. | O76: 300058 | P76: Y091AZ103 | Q76: CNE100000LV8 | R76: B3N1WC6 | S76: Reckitt Benckiser Group Plc | T76: RKT | U76: G74079107 | V76: B24CGK7 | W76: Bluefocus | X76: Johson Mead Nutrition Co | AI76: 43999
A77: CUSTOMER | B77: =C77&IF(Q77="",W77,Q77) -> GB00B24CGK77CNE100000LV8 | C77: GB00B24CGK77 | D77: =SIGN(VLOOKUP(target_uk!C77,has_scf!$E$2:$F$1366,2,FALSE)) -> 1 | E77: 43999 | F77: CUST-110159349 | G77: 194513273 | H77: 1530394 | K77: Y | M77: Johson Mead Nutrition Co | N77: BlueFocus Intelligent Communications Group Co. Ltd. | O77: 300058 | P77: Y091AZ103 | Q77: CNE100000LV8 | R77: B3N1WC6 | S77: Reckitt Benckiser Group Plc | T77: RKT | U77: G74079107 | V77: B24CGK7 | W77: Bluefocus | X77: Johson Mead Nutrition Co | AI77: 44367
A78: CUSTOMER | B78: =C78&IF(Q78="",W78,Q78) -> GB00B24CGK77US02361E1082 | C78: GB00B24CGK77 | D78: =SIGN(VLOOKUP(target_uk!C78,has_scf!$E$2:$F$1366,2,FALSE)) -> 1 | E78: 43182 | F78: CUST-110159355 | G78: 22575357 | H78: 1530394 | K78: Y | M78: Mead Johnson & Company LLC | N78: Ameresco, Inc. | O78: AMRC | P78: 2.361e+111 | Q78: US02361E1082 | R78: B3SWPT2 | S78: Reckitt Benckiser Group Plc | T78: RKT | U78: G74079107 | V78: B24CGK7 | W78: Ameresco | X78: Mead Johnson & Company | Y78: Design | Z78: build | AA78: 5-mile pipiline | AB78: landfill gas | AI78: 43899
A79: CUSTOMER | B79: =C79&IF(Q79="",W79,Q79) -> GB00B24CGK77US02361E1082 | C79: GB00B24CGK77 | D79: =SIGN(VLOOKUP(target_uk!C79,has_scf!$E$2:$F$1366,2,FALSE)) -> 1 | E79: 43899 | F79: CUST-110159355 | G79: 22575357 | H79: 1530394 | K79: Y | M79: Mead Johnson & Company LLC | N79: Ameresco, Inc. | O79: AMRC | P79: 2.361e+111 | Q79: US02361E1082 | R79: B3SWPT2 | S79: Reckitt Benckiser Group Plc | T79: RKT | U79: G74079107 | V79: B24CGK7 | W79: Ameresco | X79: Mead Johnson & Company | Y79: Design | Z79: build | AA79: 5-mile pipiline | AB79: landfill gas | AI79: 43899
A80: CUSTOMER | B80: =C80&IF(Q80="",W80,Q80) -> GB00B24CGK77LU1565283667 | C80: GB00B24CGK77 | D80: =SIGN(VLOOKUP(target_uk!C80,has_scf!$E$2:$F$1366,2,FALSE)) -> 1 | E80: 42906 | F80: CUST-110159357 | G80: 16091426 | H80: 1530394 | K80: Y | M80: JOHNSON MEAD NUTRITION CO | N80: Ardagh Group SA | O80: ARD | P80: L0223L101 | Q80: LU1565283667 | R80: BYXR9D1 | S80: Reckitt Benckiser Group Plc | T80: RKT | U80: G74079107 | V80: B24CGK7 | W80: Ardagh Group | X80: JOHNSON MEAD NUTRITION | Y80: Metal Packaging | AI80: 43894
A81: CUSTOMER | B81: =C81&IF(Q81="",W81,Q81) -> GB00B24CGK77LU1565283667 | C81: GB00B24CGK77 | D81: =SIGN(VLOOKUP(target_uk!C81,has_scf!$E$2:$F$1366,2,FALSE)) -> 1 | E81: 43894 | F81: CUST-110159357 | G81: 16091426 | H81: 1530394 | K81: Y | M81: JOHNSON MEAD NUTRITION CO | N81: Ardagh Group SA | O81: ARD | P81: L0223L101 | Q81: LU1565283667 | R81: BYXR9D1 | S81: Reckitt Benckiser Group Plc | T81: RKT | U81: G74079107 | V81: B24CGK7 | W81: Ardagh Group | X81: JOHNSON MEAD NUTRITION | Y81: Metal Packaging | AI81: 43894
A82: CUSTOMER | B82: =C82&IF(Q82="",W82,Q82) -> GB0007908733ES0129743318 | C82: GB0007908733 | D82: =SIGN(VLOOKUP(target_uk!C82,has_scf!$E$2:$F$1366,2,FALSE)) -> 0 | E82: 43365 | F82: CUST-110246011 | G82: 1837196 | H82: 1589402 | K82: Y | N82: Elecnor SA | O82: ENO | P82: E39152181 | Q82: ES0129743318 | R82: B3CTJS6 | S82: SSE Plc | T82: SSE | U82: G8842P102 | V82: 790873 | W82: Elecnor | X82: Scottish and Southern | Y82: electricity distribution | AI82: 44018
A83: CUSTOMER | B83: =C83&IF(Q83="",W83,Q83) -> GB0007908733ES0129743318 | C83: GB0007908733 | D83: =SIGN(VLOOKUP(target_uk!C83,has_scf!$E$2:$F$1366,2,FALSE)) -> 0 | E83: 44018 | F83: CUST-110246011 | G83: 1837196 | H83: 1589402 | K83: Y | N83: Elecnor SA | O83: ENO | P83: E39152181 | Q83: ES0129743318 | R83: B3CTJS6 | S83: SSE Plc | T83: SSE | U83: G8842P102 | V83: 790873 | W83: Elecnor | X83: Scottish and Southern | Y83: electricity distribution | AI83: 44018
A84: CUSTOMER | B84: =C84&IF(Q84="",W84,Q84) -> GB0031274896GB00BRJQ8J25 | C84: GB0031274896 | D84: =SIGN(VLOOKUP(target_uk!C84,has_scf!$E$2:$F$1366,2,FALSE)) -> 1 | E84: 43580 | F84: CUST-110249133 | G84: 1832308 | H84: 1603503 | J84: 1.7 | K84: Y | N84: Hammerson Plc | O84: HMSO | P84: G4273Q206 | Q84: GB00BRJQ8J25 | R84: BRJQ8J2 | S84: Marks & Spencer Group Plc | T84: MKS | U84: G5824M107 | V84: 3127489 | W84: Hammerson | X84: Marks & Spencer | Y84: tenants | AI84: 44327
A85: CUSTOMER | B85: =C85&IF(Q85="",W85,Q85) -> NL0010545661ES0129743318 | C85: NL0010545661 | D85: =SIGN(VLOOKUP(target_uk!C85,has_scf!$E$2:$F$1366,2,FALSE)) -> 0 | E85: 42909 | F85: CUST-110271312 | G85: 1837196 | H85: 194536706 | K85: Y | M85: Iveco SpA | N85: Elecnor SA | O85: ENO | P85: E39152181 | Q85: ES0129743318 | R85: B3CTJS6 | S85: CNH Industrial NV | T85: CNH | U85: N20944109 | V85: BDX85Z1 | W85: Elecnor | X85: Iveco | Y85: Automotive | AI85: 44490
A86: CUSTOMER | B86: =C86&IF(Q86="",W86,Q86) -> NL0010545661NO0010571680 | C86: NL0010545661 | D86: =SIGN(VLOOKUP(target_uk!C86,has_scf!$E$2:$F$1366,2,FALSE)) -> 0 | E86: 42913 | F86: CUST-110346979 | G86: 194503420 | H86: 194536706 | K86: Y | N86: Wallenius Wilhelmsen ASA | O86: WAWI | P86: R9820L103 | Q86: NO0010571680 | R86: B55WMQ5 | S86: CNH Industrial NV | T86: CNH | U86: N20944109 | V86: BDX85Z1 | W86: Wilh. Wilhelmsen | X86: CNH Industrial | Y86: High & Heavy | AI86: 43944
A87: CUSTOMER | B87: =C87&IF(Q87="",W87,Q87) -> NL0010545661NO0010571680 | C87: NL0010545661 | D87: =SIGN(VLOOKUP(target_uk!C87,has_scf!$E$2:$F$1366,2,FALSE)) -> 0 | E87: 43944 | F87: CUST-110346979 | G87: 194503420 | H87: 194536706 | K87: Y | N87: Wallenius Wilhelmsen ASA | O87: WAWI | P87: R9820L103 | Q87: NO0010571680 | R87: B55WMQ5 | S87: CNH Industrial NV | T87: CNH | U87: N20944109 | V87: BDX85Z1 | W87: Wilh. Wilhelmsen | X87: CNH Industrial | Y87: High & Heavy | AI87: 43944
A88: CUSTOMER | B88: =C88&IF(Q88="",W88,Q88) -> GB00B7KR2P84IT0001490736 | C88: GB00B7KR2P84 | D88: =SIGN(VLOOKUP(target_uk!C88,has_scf!$E$2:$F$1366,2,FALSE)) -> 0 | E88: 42913 | F88: CUST-110359294 | G88: 22441006 | H88: 1634656 | K88: Y | N88: SAVE SpA | O88: SAVE | P88: T81213109 | Q88: IT0001490736 | R88: B08F437 | S88: easyJet Plc | T88: EZJ | U88: G3030S109 | V88: B7KR2P8 | W88: Save | X88: easyJet | Y88: Venice | Z88: new operations | AA88: main carrier | AI88: 45405
A89: CUSTOMER | B89: =C89&IF(Q89="",W89,Q89) -> GB00B1722W11IT0001490736 | C89: GB00B1722W11 | D89: =SIGN(VLOOKUP(target_uk!C89,has_scf!$E$2:$F$1366,2,FALSE)) -> 0 | E89: 42913 | F89: CUST-110372144 | G89: 22441006 | H89: 194508808 | K89: Y | M89: Jet2.com Ltd. | N89: SAVE SpA | O89: SAVE | P89: T81213109 | Q89: IT0001490736 | R89: B08F437 | S89: Jet2 Plc | T89: JET2 | U89: G5112P101 | V89: B1722W1 | W89: Save | X89: Jet2.com | Y89: point to point | AI89: 45405
A90: CUSTOMER | B90: =C90&IF(Q90="",W90,Q90) -> GB0007188757NL0000888691 | C90: GB0007188757 | D90: =SIGN(VLOOKUP(target_uk!C90,has_scf!$E$2:$F$1366,2,FALSE)) -> 1 | E90: 42964 | F90: CUST-112524365 | G90: 1918644 | H90: 8792 | K90: Y | N90: AMG Critical Materials NV | O90: AMG | P90: N04897109 | Q90: NL0000888691 | R90: B1Z95S1 | S90: Rio Tinto Plc | T90: RIO | U90: G75754104 | V90: 718875 | W90: AMG Advanced Metallurgical | X90: Rio Tinto | Y90: aluminum master alloys and powders | AI90: 44637
A91: CUSTOMER | B91: =C91&IF(Q91="",W91,Q91) -> GB00B24CGK77FI0009010862 | C91: GB00B24CGK77 | D91: =SIGN(VLOOKUP(target_uk!C91,has_scf!$E$2:$F$1366,2,FALSE)) -> 1 | E91: 42965 | F91: CUST-112575918 | G91: 194504635 | H91: 1530394 | K91: Y | N91: Suominen Oyj | O91: SUY1V | P91: X87937110 | Q91: FI0009010862 | R91: 7051197 | S91: Reckitt Benckiser Group Plc | T91: RKT | U91: G74079107 | V91: B24CGK7 | W91: Suominen | X91: Reckitt Benckiser Group | Y91: nonwovens | AI91: 44278
A92: CUSTOMER | B92: =C92&IF(Q92="",W92,Q92) -> GB0004915632GB0002015021 | C92: GB0004915632 | D92: =SIGN(VLOOKUP(target_uk!C92,has_scf!$E$2:$F$1366,2,FALSE)) -> 1 | E92: 42965 | F92: CUST-112582962 | G92: 1832232 | H92: 1832354 | K92: Y | N92: TClarke Plc | O92: CTO | P92: G87012103 | Q92: GB0002015021 | R92: 201502 | S92: Kier Group Plc | T92: KIE | U92: G52549105 | V92: 491563 | W92: T. Clarke | X92: Kier Group | Y92: principal contractors | Z92: property owners and developers | AA92: Barratt Homes | AI92: 43984
A93: CUSTOMER | B93: =C93&IF(Q93="",W93,Q93) -> GB0004915632GB0002015021 | C93: GB0004915632 | D93: =SIGN(VLOOKUP(target_uk!C93,has_scf!$E$2:$F$1366,2,FALSE)) -> 1 | E93: 43984 | F93: CUST-112582962 | G93: 1832232 | H93: 1832354 | K93: Y | N93: TClarke Plc | O93: CTO | P93: G87012103 | Q93: GB0002015021 | R93: 201502 | S93: Kier Group Plc | T93: KIE | U93: G52549105 | V93: 491563 | W93: T. Clarke | X93: Kier Group | Y93: principal contractors | Z93: property owners and developers | AA93: Barratt Homes | AI93: 43984
A94: CUSTOMER | B94: =C94&IF(Q94="",W94,Q94) -> GB00BNG2M159CNE000001N62 | C94: GB00BNG2M159 | D94: =SIGN(VLOOKUP(target_uk!C94,has_scf!$E$2:$F$1366,2,FALSE)) -> 0 | E94: 42965 | F94: CUST-112588499 | G94: 1885375 | H94: 1921772 | K94: Y | N94: Shenzhen Deren Electronic Co., Ltd. | O94: 2055 | P94: Y7740E102 | Q94: CNE000001N62 | R94: B19H730 | S94: Allianz Technology Trust Plc | T94: ATT | U94: G0258S118 | V94: BNG2M15 | W94: Shenzhen Deren Electronic | X94: RCM Technology | Y94: electronic connectors and precision components | AI94: 44889
A95: CUSTOMER | B95: =C95&IF(Q95="",W95,Q95) -> GB0000055888US7434651060 | C95: GB0000055888 | D95: =SIGN(VLOOKUP(target_uk!C95,has_scf!$E$2:$F$1366,2,FALSE)) -> 1 | E95: 42969 | F95: CUST-112670433 | G95: 9676 | H95: 1819438 | K95: Y | M95: ACAL BFI | N95: ProPhotonix Ltd. | O95: STKR | P95: 743465106 | Q95: US7434651060 | R95: 2566890 | S95: discoverIE Group Plc | T95: DSCV | U95: G2887F103 | V95: 5588 | W95: Prophotonix | X95: discoverIE | Y95: Laser modules | AI95: 44494
A96: CUSTOMER | B96: =C96&IF(Q96="",W96,Q96) -> GB0031274896FR0010282822 | C96: GB0031274896 | D96: =SIGN(VLOOKUP(target_uk!C96,has_scf!$E$2:$F$1366,2,FALSE)) -> 1 | E96: 42970 | F96: CUST-112708395 | G96: 1923351 | H96: 1603503 | K96: Y | N96: VusionGroup SA | O96: VU | P96: F8333P109 | Q96: FR0010282822 | R96: B0XMRC3 | S96: Marks & Spencer Group Plc | T96: MKS | U96: G5824M107 | V96: 3127489 | W96: Store Electronic Systems | X96: Marks & Spencer | Y96: Electronic shelf labels | AI96: 44054
A97: CUSTOMER | B97: =C97&IF(Q97="",W97,Q97) -> GB0031274896FR0010282822 | C97: GB0031274896 | D97: =SIGN(VLOOKUP(target_uk!C97,has_scf!$E$2:$F$1366,2,FALSE)) -> 1 | E97: 44054 | F97: CUST-112708395 | G97: 1923351 | H97: 1603503 | K97: Y | N97: VusionGroup SA | O97: VU | P97: F8333P109 | Q97: FR0010282822 | R97: B0XMRC3 | S97: Marks & Spencer Group Plc | T97: MKS | U97: G5824M107 | V97: 3127489 | W97: Store Electronic Systems | X97: Marks & Spencer | Y97: Electronic shelf labels | AI97: 44054
A98: CUSTOMER | B98: =C98&IF(Q98="",W98,Q98) -> GB0007188757JE00B5SJJD95 | C98: GB0007188757 | D98: =SIGN(VLOOKUP(target_uk!C98,has_scf!$E$2:$F$1366,2,FALSE)) -> 1 | E98: 43019 | F98: CUST-114539552 | G98: 194516217 | H98: 8792 | K98: Y | N98: Cape Intermediate Holdings Ltd. | O98: CIU | P98: G1933N102 | Q98: JE00B5SJJD95 | R98: B5SJJD9 | S98: Rio Tinto Plc | T98: RIO | U98: G75754104 | V98: 718875 | W98: Cape | X98: Rio Tinto | Y98: Australia | Z98: industrial | AI98: 767011
A99: CUSTOMER | B99: =C99&IF(Q99="",W99,Q99) -> GB0030927254GB00BZ0D6727 | C99: GB0030927254 | D99: =SIGN(VLOOKUP(target_uk!C99,has_scf!$E$2:$F$1366,2,FALSE)) -> 0 | E99: 43021 | F99: CUST-114674033 | G99: 76868922 | H99: 194517741 | K99: Y | N99: Kainos Group Plc | O99: KNOS | P99: G5209U104 | Q99: GB00BZ0D6727 | R99: BZ0D672 | S99: ASOS Plc | T99: ASC | U99: G0536Q108 | V99: 3092725 | W99: Kainos Group | X99: ASOS | Y99: Workday | AI99: 44277
A100: CUSTOMER | B100: =C100&IF(Q100="",W100,Q100) -> GB00BTC0LB89GB00B4WFW713 | C100: GB00BTC0LB89 | D100: =SIGN(VLOOKUP(target_uk!C100,has_scf!$E$2:$F$1366,2,FALSE)) -> 0 | E100: 43304 | F100: CUST-114741270 | G100: 194525724 | H100: 71914378 | J100: 3.6 | K100: Y | M100: DFS | N100: LondonMetric Property Plc | O100: LMP | P100: G5689W109 | Q100: GB00B4WFW713 | R100: B4WFW71 | S100: DFS Furniture Plc | T100: DFS | U100: G2848C108 | V100: BTC0LB8 | W100: London & Stamford | X100: DFS Furniture | Y100: Top ten occupier | AI100: 43881
...

Sheet source_uk
A1: rel_type | B1: column_4_doublecounting | C1: source_isin | D1: has_scf | E1: start_ | F1: id | G1: source_company_id | H1: target_company_id | I1: subsidiaries | J1: revenue_percent | K1: percent_estimated | L1: source_company_subsidiaries | M1: target_company_subsidiaries | N1: source_name | O1: source_ticker | P1: source_cusip | Q1: source_sedol | R1: target_name | S1: target_ticker | T1: target_cusip | U1: target_isin | V1: target_sedol | W1: source_company_keyword | X1: target_company_keyword | Y1: keyword1 | Z1: keyword2 | AA1: keyword3 | AB1: keyword4 | AC1: keyword5 | AD1: keyword6 | AE1: keyword7 | AF1: keyword8 | AG1: keyword9 | AH1: keyword10 | AI1: end_
A2: SUPPLIER | B2: =C2&IF(U2="",R2,U2) -> GB0006615826Chelverton Asset Management Ltd. | C2: GB0006615826 | D2: =SIGN(VLOOKUP(C2,has_scf!$E$2:$F$1366,2,FALSE)) -> 0 | E2: 42786 | F2: SUPPL-104775748 | G2: 1921493 | H2: 8206680 | K2: Y | N2: Chelverton UK Dividend Trust Plc | O2: SDV | P2: G8185S119 | Q2: 661582 | R2: Chelverton Asset Management Ltd. | W2: Small Companies Dividend Trust | Y2: Investment Manager | AI2: 45211
A3: SUPPLIER | B3: =C3&IF(U3="",R3,U3) -> GB00BSBMW716CH0025238863 | C3: GB00BSBMW716 | D3: =SIGN(VLOOKUP(C3,has_scf!$E$2:$F$1366,2,FALSE)) -> 0 | E3: 42787 | F3: SUPPL-104811647 | G3: 69517152 | H3: 8930788 | K3: Y | N3: Focusrite Plc | O3: TUNE | P3: G3610N108 | Q3: BSBMW71 | R3: KÃ¼hne + Nagel International AG | S3: KNIN | T3: H4673L145 | U3: CH0025238863 | V3: B142S60 | W3: focusrite plc | X3: Kuehne & Nagel | Y3: logistics | AI3: 44161
A4: SUPPLIER | B4: =C4&IF(U4="",R4,U4) -> GB00BSBMW716CH0025238863 | C4: GB00BSBMW716 | D4: =SIGN(VLOOKUP(C4,has_scf!$E$2:$F$1366,2,FALSE)) -> 0 | E4: 44161 | F4: SUPPL-104811647 | G4: 69517152 | H4: 8930788 | K4: Y | N4: Focusrite Plc | O4: TUNE | P4: G3610N108 | Q4: BSBMW71 | R4: KÃ¼hne + Nagel International AG | S4: KNIN | T4: H4673L145 | U4: CH0025238863 | V4: B142S60 | W4: focusrite plc | X4: Kuehne & Nagel | Y4: logistics | AI4: 44161
A5: SUPPLIER | B5: =C5&IF(U5="",R5,U5) -> GB00BSBMW716Gibson Brands, Inc. | C5: GB00BSBMW716 | D5: =SIGN(VLOOKUP(C5,has_scf!$E$2:$F$1366,2,FALSE)) -> 0 | E5: 42787 | F5: SUPPL-104816680 | G5: 69517152 | H5: 9443989 | K5: Y | M5: KRK Systems LLC | N5: Focusrite Plc | O5: TUNE | P5: G3610N108 | Q5: BSBMW71 | R5: Gibson Brands, Inc. | W5: focusrite plc | X5: KRK Systems LLC | Y5: monitors | AI5: 44180
A6: SUPPLIER | B6: =C6&IF(U6="",R6,U6) -> GB00BSBMW716Gibson Brands, Inc. | C6: GB00BSBMW716 | D6: =SIGN(VLOOKUP(C6,has_scf!$E$2:$F$1366,2,FALSE)) -> 0 | E6: 44180 | F6: SUPPL-104816680 | G6: 69517152 | H6: 9443989 | K6: Y | M6: KRK Systems LLC | N6: Focusrite Plc | O6: TUNE | P6: G3610N108 | Q6: BSBMW71 | R6: Gibson Brands, Inc. | W6: focusrite plc | X6: KRK Systems LLC | Y6: monitors | AI6: 44180
A7: SUPPLIER | B7: =C7&IF(U7="",R7,U7) -> GB00BSBMW716Ableton AG | C7: GB00BSBMW716 | D7: =SIGN(VLOOKUP(C7,has_scf!$E$2:$F$1366,2,FALSE)) -> 0 | E7: 42787 | F7: SUPPL-104816806 | G7: 69517152 | H7: 7096310 | K7: Y | N7: Focusrite Plc | O7: TUNE | P7: G3610N108 | Q7: BSBMW71 | R7: Ableton AG | W7: focusrite plc | X7: Ableton | AI7: 44161
A8: SUPPLIER | B8: =C8&IF(U8="",R8,U8) -> GB00BSBMW716Ableton AG | C8: GB00BSBMW716 | D8: =SIGN(VLOOKUP(C8,has_scf!$E$2:$F$1366,2,FALSE)) -> 0 | E8: 44161 | F8: SUPPL-104816806 | G8: 69517152 | H8: 7096310 | K8: Y | N8: Focusrite Plc | O8: TUNE | P8: G3610N108 | Q8: BSBMW71 | R8: Ableton AG | W8: focusrite plc | X8: Ableton | AI8: 44161
A9: SUPPLIER | B9: =C9&IF(U9="",R9,U9) -> GB00BSBMW716Gibson Brands, Inc. | C9: GB00BSBMW716 | D9: =SIGN(VLOOKUP(C9,has_scf!$E$2:$F$1366,2,FALSE)) -> 0 | E9: 42787 | F9: SUPPL-104817198 | G9: 69517152 | H9: 9443989 | K9: Y | M9: Stanton Magnetics Inc | N9: Focusrite Plc | O9: TUNE | P9: G3610N108 | Q9: BSBMW71 | R9: Gibson Brands, Inc. | W9: focusrite plc | X9: Stanton Magnetics | AI9: 44180
A10: SUPPLIER | B10: =C10&IF(U10="",R10,U10) -> GB00BSBMW716Gibson Brands, Inc. | C10: GB00BSBMW716 | D10: =SIGN(VLOOKUP(C10,has_scf!$E$2:$F$1366,2,FALSE)) -> 0 | E10: 44180 | F10: SUPPL-104817198 | G10: 69517152 | H10: 9443989 | K10: Y | M10: Stanton Magnetics Inc | N10: Focusrite Plc | O10: TUNE | P10: G3610N108 | Q10: BSBMW71 | R10: Gibson Brands, Inc. | W10: focusrite plc | X10: Stanton Magnetics | AI10: 44180
A11: SUPPLIER | B11: =C11&IF(U11="",R11,U11) -> GB00BSBMW716Gibson Brands, Inc. | C11: GB00BSBMW716 | D11: =SIGN(VLOOKUP(C11,has_scf!$E$2:$F$1366,2,FALSE)) -> 0 | E11: 42787 | F11: SUPPL-104817256 | G11: 69517152 | H11: 9443989 | K11: Y | M11: Cerwin-Vega Inc | N11: Focusrite Plc | O11: TUNE | P11: G3610N108 | Q11: BSBMW71 | R11: Gibson Brands, Inc. | W11: focusrite plc | X11: Cerwin-Vega | AI11: 44180
A12: SUPPLIER | B12: =C12&IF(U12="",R12,U12) -> GB00BSBMW716Gibson Brands, Inc. | C12: GB00BSBMW716 | D12: =SIGN(VLOOKUP(C12,has_scf!$E$2:$F$1366,2,FALSE)) -> 0 | E12: 44180 | F12: SUPPL-104817256 | G12: 69517152 | H12: 9443989 | K12: Y | M12: Cerwin-Vega Inc | N12: Focusrite Plc | O12: TUNE | P12: G3610N108 | Q12: BSBMW71 | R12: Gibson Brands, Inc. | W12: focusrite plc | X12: Cerwin-Vega | AI12: 44180
A13: SUPPLIER | B13: =C13&IF(U13="",R13,U13) -> GB00BSBMW716 | C13: GB00BSBMW716 | D13: =SIGN(VLOOKUP(C13,has_scf!$E$2:$F$1366,2,FALSE)) -> 0 | E13: 42796 | F13: SUPPL-105319671 | G13: 69517152 | H13: 105319400 | K13: Y | N13: Focusrite Plc | O13: TUNE | P13: G3610N108 | Q13: BSBMW71 | W13: focusrite plc | X13: sE Electronics International | Y13: Distribution | AI13: 45664
A14: SUPPLIER | B14: =C14&IF(U14="",R14,U14) -> GB00BQFH6320Government of France | C14: GB00BQFH6320 | D14: =SIGN(VLOOKUP(C14,has_scf!$E$2:$F$1366,2,FALSE)) -> 0 | E14: 42948 | F14: SUPPL-111887319 | G14: 85326175 | H14: 228636 | K14: Y | M14: City of Cannes | N14: Ascential Plc | O14: ASCL | P14: G0519H166 | Q14: BQFH632 | R14: Government of France | W14: Ascential | X14: City of Cannes | Y14: venue | AI14: 43952
A15: SUPPLIER | B15: =C15&IF(U15="",R15,U15) -> GB00BQFH6320Government of France | C15: GB00BQFH6320 | D15: =SIGN(VLOOKUP(C15,has_scf!$E$2:$F$1366,2,FALSE)) -> 0 | E15: 43952 | F15: SUPPL-111887319 | G15: 85326175 | H15: 228636 | K15: Y | M15: City of Cannes | N15: Ascential Plc | O15: ASCL | P15: G0519H166 | Q15: BQFH632 | R15: Government of France | W15: Ascential | X15: City of Cannes | Y15: venue | AI15: 43952
A16: SUPPLIER | B16: =C16&IF(U16="",R16,U16) -> GB00BYQ94H38The University of Nottingham | C16: GB00BYQ94H38 | D16: =SIGN(VLOOKUP(C16,has_scf!$E$2:$F$1366,2,FALSE)) -> 0 | E16: 42949 | F16: SUPPL-111965556 | G16: 89910202 | H16: 245376 | K16: Y | N16: Oncimmune Holdings Plc | O16: ONC | P16: G6750T108 | Q16: BYQ94H3 | R16: The University of Nottingham | W16: Oncimmune | X16: University of Nottingham | Y16: facilities | Z16: research | AI16: 45406
A17: SUPPLIER | B17: =C17&IF(U17="",R17,U17) -> GB0059337583 | C17: GB0059337583 | D17: =SIGN(VLOOKUP(C17,has_scf!$E$2:$F$1366,2,FALSE)) -> 0 | E17: 43075 | F17: SUPPL-117614041 | G17: 194516577 | H17: 1915 | K17: Y | N17: Deltex Medical Group Plc | O17: DEMG | P17: G2709P107 | Q17: 3103865 | W17: Deltex Medical | X17: CAS Medical Systems | Y17: UK | Z17: cerebral oximetry monitoring market | AA17: exclusive distribution | AB17: CASMED | AC17: FORE-SIGHT cerebral oximeter monitors | AD17: Ireland | AI17: 44032
A18: SUPPLIER | B18: =C18&IF(U18="",R18,U18) -> GB0059337583 | C18: GB0059337583 | D18: =SIGN(VLOOKUP(C18,has_scf!$E$2:$F$1366,2,FALSE)) -> 0 | E18: 44032 | F18: SUPPL-117614041 | G18: 194516577 | H18: 1915 | K18: Y | N18: Deltex Medical Group Plc | O18: DEMG | P18: G2709P107 | Q18: 3103865 | W18: Deltex Medical | X18: CAS Medical Systems | Y18: UK | Z18: cerebral oximetry monitoring market | AA18: exclusive distribution | AB18: CASMED | AC18: FORE-SIGHT cerebral oximeter monitors | AD18: Ireland | AI18: 44032
A19: SUPPLIER | B19: =C19&IF(U19="",R19,U19) -> GB00B7KR2P84DE0005552004 | C19: GB00B7KR2P84 | D19: =SIGN(VLOOKUP(C19,has_scf!$E$2:$F$1366,2,FALSE)) -> 0 | E19: 43488 | F19: SUPPL-117980002 | G19: 1634656 | H19: 1557283 | K19: Y | M19: DHL Express | N19: easyJet Plc | O19: EZJ | P19: G3030S109 | Q19: B7KR2P8 | R19: Deutsche Post AG | S19: DHL | T19: D19225107 | U19: DE0005552004 | V19: 4617859 | W19: easyJet | X19: Deutsche Post | Y19: Ground Handling | AI19: 45637
A20: SUPPLIER | B20: =C20&IF(U20="",R20,U20) -> GB00BY7R8K77GB00BP9LHF23 | C20: GB00BY7R8K77 | D20: =SIGN(VLOOKUP(C20,has_scf!$E$2:$F$1366,2,FALSE)) -> 0 | E20: 43809 | F20: SUPPL-104128606 | G20: 82444487 | H20: 1732173 | K20: Y | N20: Schroder European Real Estate Investment Trust Plc | O20: SERE | P20: G7856Y108 | Q20: BY7R8K7 | R20: Schroders Plc | S20: SDR | T20: G78602144 | U20: GB00BP9LHF23 | V20: BP9LHF2 | W20: schroder european real estate investment trust plc | X20: Schroders | Y20: Substantial share interests | AI20: 45405
A21: SUPPLIER | B21: =C21&IF(U21="",R21,U21) -> GB00BSB7BS06 | C21: GB00BSB7BS06 | D21: =SIGN(VLOOKUP(C21,has_scf!$E$2:$F$1366,2,FALSE)) -> 0 | E21: 43565 | F21: SUPPL-104169882 | G21: 1832424 | H21: 9556323 | K21: Y | L21: Evans Halshaw Ltd. | M21: Automobiles Citroen SA | N21: Pinewood Technologies Group Plc | O21: PINE | P21: G6986L192 | Q21: BSB7BS0 | W21: Evans Halshaw | X21: Automobiles Citroen | AI21: 44216
A22: SUPPLIER | B22: =C22&IF(U22="",R22,U22) -> GB00BSB7BS06 | C22: GB00BSB7BS06 | D22: =SIGN(VLOOKUP(C22,has_scf!$E$2:$F$1366,2,FALSE)) -> 0 | E22: 44216 | F22: SUPPL-104169882 | G22: 1832424 | H22: 9556323 | K22: Y | L22: Evans Halshaw Ltd. | M22: Automobiles Citroen SA | N22: Pinewood Technologies Group Plc | O22: PINE | P22: G6986L192 | Q22: BSB7BS0 | W22: Evans Halshaw | X22: Automobiles Citroen | AI22: 44216
A23: SUPPLIER | B23: =C23&IF(U23="",R23,U23) -> GB00B0744B38 | C23: GB00B0744B38 | D23: =SIGN(VLOOKUP(C23,has_scf!$E$2:$F$1366,2,FALSE)) -> 0 | E23: 42886 | F23: SUPPL-109397977 | G23: 1302 | H23: 8453544 | K23: Y | N23: Bunzl Plc | O23: BNZL | P23: G16968110 | Q23: B0744B3 | W23: Bunzl | Y23: Global Sourcing | AI23: 44300
A24: SUPPLIER | B24: =C24&IF(U24="",R24,U24) -> GB0031429219JE00BYPZJM29 | C24: GB0031429219 | D24: =SIGN(VLOOKUP(C24,has_scf!$E$2:$F$1366,2,FALSE)) -> 0 | E24: 43243 | F24: SUPPL-109459191 | G24: 1921502 | H24: 109351491 | K24: Y | M24: Janus Henderson Investors | N24: Law Debenture Corp. Plc | O24: LWDB | P24: G53900125 | Q24: 3142921 | R24: Janus Henderson Group Plc | S24: JHG | T24: G4474Y214 | U24: JE00BYPZJM29 | V24: BYPZJQ6 | W24: The Law Debenture | X24: Janus Henderson Group | Y24: Investment manager | AI24: 44281
A25: SUPPLIER | B25: =C25&IF(U25="",R25,U25) -> GB00BN4NDR39JE00BYPZJM29 | C25: GB00BN4NDR39 | D25: =SIGN(VLOOKUP(C25,has_scf!$E$2:$F$1366,2,FALSE)) -> 0 | E25: 42887 | F25: SUPPL-109459198 | G25: 1921762 | H25: 109351491 | K25: Y | M25: Henderson Investment Funds Limited | N25: The Bankers Investment Trust Plc | O25: BNKR | P25: G07476123 | Q25: BN4NDR3 | R25: Janus Henderson Group Plc | S25: JHG | T25: G4474Y214 | U25: JE00BYPZJM29 | V25: BYPZJQ6 | W25: Bankers Investment Trust | X25: Henderson Investment Funds Limited | Y25: Alternative Investment Fund Manager | Z25: AIFMD | AA25: HIFL | AI25: 44950
A26: SUPPLIER | B26: =C26&IF(U26="",R26,U26) -> GB0001990497JE00BYPZJM29 | C26: GB0001990497 | D26: =SIGN(VLOOKUP(C26,has_scf!$E$2:$F$1366,2,FALSE)) -> 0 | E26: 43049 | F26: SUPPL-109459206 | G26: 16001353 | H26: 109351491 | K26: Y | M26: Henderson Investment Funds Limited | N26: The City of London Investment Trust Plc | O26: CTY | P26: G90260103 | Q26: 199049 | R26: Janus Henderson Group Plc | S26: JHG | T26: G4474Y214 | U26: JE00BYPZJM29 | V26: BYPZJQ6 | W26: The City of London Investment Trust PLC | X26: Janus Henderson Fund Management | Y26: Alternative Investment Fund Manager | AI26: 45937
A27: SUPPLIER | B27: =C27&IF(U27="",R27,U27) -> GB00BLSNGB01JE00BYPZJM29 | C27: GB00BLSNGB01 | D27: =SIGN(VLOOKUP(C27,has_scf!$E$2:$F$1366,2,FALSE)) -> 0 | E27: 42887 | F27: SUPPL-109459244 | G27: 16001008 | H27: 109351491 | K27: Y | M27: Henderson Investment Funds Limited | N27: Henderson European Trust Plc | O27: HET | P27: G4464P116 | Q27: BLSNGB0 | R27: Janus Henderson Group Plc | S27: JHG | T27: G4474Y214 | U27: JE00BYPZJM29 | V27: BYPZJQ6 | W27: Henderson | X27: Henderson Investment Funds Limited | Y27: Alternative Investment Fund Manager | AI27: 45405
A28: SUPPLIER | B28: =C28&IF(U28="",R28,U28) -> GB00BNXGHS27JE00BYPZJM29 | C28: GB00BNXGHS27 | D28: =SIGN(VLOOKUP(C28,has_scf!$E$2:$F$1366,2,FALSE)) -> 0 | E28: 42887 | F28: SUPPL-109459248 | G28: 1921507 | H28: 109351491 | K28: Y | M28: Henderson Investment Funds Limited | N28: Lowland Investment Co. Plc | O28: LWI | P28: G56784112 | Q28: BNXGHS2 | R28: Janus Henderson Group Plc | S28: JHG | T28: G4474Y214 | U28: JE00BYPZJM29 | V28: BYPZJQ6 | W28: Lowland Investment | X28: Janus Henderson Fund Management | Y28: Alternative Investment Fund Manager | AI28: 44925
A29: SUPPLIER | B29: =C29&IF(U29="",R29,U29) -> GB0009580571JE00BYPZJM29 | C29: GB0009580571 | D29: =SIGN(VLOOKUP(C29,has_scf!$E$2:$F$1366,2,FALSE)) -> 0 | E29: 42887 | F29: SUPPL-109459266 | G29: 1921688 | H29: 109351491 | K29: Y | M29: Henderson Investment Funds Limited | N29: Henderson High Income Trust Plc | O29: HHI | P29: G4464B109 | Q29: 958057 | R29: Janus Henderson Group Plc | S29: JHG | T29: G4474Y214 | U29: JE00BYPZJM29 | V29: BYPZJQ6 | W29: Henderson High Income Trust | X29: Henderson Investment Funds Limited | Y29: Alternative Investment Fund Manager | AI29: 44361
A30: SUPPLIER | B30: =C30&IF(U30="",R30,U30) -> GB00B0LCW083FI0009014377 | C30: GB00B0LCW083 | D30: =SIGN(VLOOKUP(C30,has_scf!$E$2:$F$1366,2,FALSE)) -> 0 | E30: 43937 | F30: SUPPL-109655342 | G30: 1832305 | H30: 22440304 | K30: Y | N30: Hikma Pharmaceuticals Plc | O30: HIK | P30: G4576K104 | Q30: B0LCW08 | R30: Orion Oyj | S30: ORNBV | T30: X6002Y112 | U30: FI0009014377 | V30: B17NY40 | W30: Hikma Pharmaceuticals | X30: Orion | Y30: Bufomix easyhaler | AI30: 45006
A31: SUPPLIER | B31: =C31&IF(U31="",R31,U31) -> GB00BV9FP302Vidyo, Inc. | C31: GB00BV9FP302 | D31: =SIGN(VLOOKUP(C31,has_scf!$E$2:$F$1366,2,FALSE)) -> 1 | E31: 42895 | F31: SUPPL-109778656 | G31: 1625707 | H31: 26531675 | K31: Y | N31: Computacenter Plc | O31: CCC | P31: G23356150 | Q31: BV9FP30 | R31: Vidyo, Inc. | W31: Computacenter | X31: Vidyo | Y31: Conferencing solutions | AI31: 44790
A32: SUPPLIER | B32: =C32&IF(U32="",R32,U32) -> GB00BM8Q5M07Sportswear Co. SpA | C32: GB00BM8Q5M07 | D32: =SIGN(VLOOKUP(C32,has_scf!$E$2:$F$1366,2,FALSE)) -> 0 | E32: 43263 | F32: SUPPL-113829538 | G32: 1832342 | H32: 112088400 | K32: Y | L32: Tessuti Ltd. | N32: JD Sports Fashion Plc | O32: JD | P32: G5144Y120 | Q32: BM8Q5M0 | R32: Sportswear Co. SpA | W32: Tessuti | X32: sportswear spa | Y32: Stone Island | Z32: footwear | AA32: accessories | AB32: apparel | AI32: 44820
A33: SUPPLIER | B33: =C33&IF(U33="",R33,U33) -> GB00B1GK4645DE0007100000 | C33: GB00B1GK4645 | D33: =SIGN(VLOOKUP(C33,has_scf!$E$2:$F$1366,2,FALSE)) -> 0 | E33: 43027 | F33: SUPPL-114921373 | G33: 194521070 | H33: 19337 | K33: Y | M33: Mercedes-Benz | N33: Vertu Motors Plc | O33: VTU | P33: G9337V109 | Q33: B1GK464 | R33: Mercedes-Benz Group AG | S33: MBG | T33: D1668R123 | U33: DE0007100000 | V33: 5529027 | W33: Vertu Motors | X33: Mercedez-Benz | AI33: 44780
A34: SUPPLIER | B34: =C34&IF(U34="",R34,U34) -> GB00B1GK4645JP3633400001 | C34: GB00B1GK4645 | D34: =SIGN(VLOOKUP(C34,has_scf!$E$2:$F$1366,2,FALSE)) -> 0 | E34: 43027 | F34: SUPPL-114921937 | G34: 194521070 | H34: 10260 | K34: Y | N34: Vertu Motors Plc | O34: VTU | P34: G9337V109 | Q34: B1GK464 | R34: Toyota Motor Corp. | S34: 7203 | T34: J92676113 | U34: JP3633400001 | V34: 6900643 | W34: Vertu Motors | X34: Toyota | AI34: 44780
A35: SUPPLIER | B35: =C35&IF(U35="",R35,U35) -> GB00B1GK4645DE0006757008 | C35: GB00B1GK4645 | D35: =SIGN(VLOOKUP(C35,has_scf!$E$2:$F$1366,2,FALSE)) -> 0 | E35: 43027 | F35: SUPPL-114922954 | G35: 194521070 | H35: 19299200 | K35: Y | N35: Vertu Motors Plc | O35: VTU | P35: G9337V109 | Q35: B1GK464 | R35: AUDI AG | S35: NSU | T35: D04312100 | U35: DE0006757008 | V35: 5761498 | W35: Vertu Motors | X35: Audi | AI35: 44780
A36: SUPPLIER | B36: =C36&IF(U36="",R36,U36) -> GB00BCRX1J15FR0010411983 | C36: GB00BCRX1J15 | D36: =SIGN(VLOOKUP(C36,has_scf!$E$2:$F$1366,2,FALSE)) -> 0 | E36: 43028 | F36: SUPPL-115039002 | G36: 89242004 | H36: 9083 | K36: Y | M36: SCOR Life Global Life (UK Branch). | N36: Just Group Plc | O36: JUST | P36: G9331B109 | Q36: BCRX1J1 | R36: SCOR SE | S36: SCR | T36: F15561677 | U36: FR0010411983 | V36: B1LB9P6 | W36: jrp group plc | X36: SCOR | Y36: reinsurers | AI36: 43958
A37: SUPPLIER | B37: =C37&IF(U37="",R37,U37) -> GB00BCRX1J15FR0010411983 | C37: GB00BCRX1J15 | D37: =SIGN(VLOOKUP(C37,has_scf!$E$2:$F$1366,2,FALSE)) -> 0 | E37: 43958 | F37: SUPPL-115039002 | G37: 89242004 | H37: 9083 | K37: Y | M37: SCOR Life Global Life (UK Branch). | N37: Just Group Plc | O37: JUST | P37: G9331B109 | Q37: BCRX1J1 | R37: SCOR SE | S37: SCR | T37: F15561677 | U37: FR0010411983 | V37: B1LB9P6 | W37: jrp group plc | X37: SCOR | Y37: reinsurers | AI37: 43958
A38: SUPPLIER | B38: =C38&IF(U38="",R38,U38) -> GB00BCRX1J15 | C38: GB00BCRX1J15 | D38: =SIGN(VLOOKUP(C38,has_scf!$E$2:$F$1366,2,FALSE)) -> 0 | E38: 43028 | F38: SUPPL-115039160 | G38: 89242004 | H38: 6266508 | K38: Y | N38: Just Group Plc | O38: JUST | P38: G9331B109 | Q38: BCRX1J1 | W38: jrp group plc | Y38: Reinsurers | AI38: 43958
A39: SUPPLIER | B39: =C39&IF(U39="",R39,U39) -> GB00BCRX1J15 | C39: GB00BCRX1J15 | D39: =SIGN(VLOOKUP(C39,has_scf!$E$2:$F$1366,2,FALSE)) -> 0 | E39: 43958 | F39: SUPPL-115039160 | G39: 89242004 | H39: 6266508 | K39: Y | N39: Just Group Plc | O39: JUST | P39: G9331B109 | Q39: BCRX1J1 | W39: jrp group plc | Y39: Reinsurers | AI39: 43958
A40: SUPPLIER | B40: =C40&IF(U40="",R40,U40) -> GB00BCRX1J15US0846707026 | C40: GB00BCRX1J15 | D40: =SIGN(VLOOKUP(C40,has_scf!$E$2:$F$1366,2,FALSE)) -> 0 | E40: 43028 | F40: SUPPL-115039199 | G40: 89242004 | H40: 1319 | K40: Y | M40: General Reinsurance AG (London branch) | N40: Just Group Plc | O40: JUST | P40: G9331B109 | Q40: BCRX1J1 | R40: Berkshire Hathaway, Inc. | S40: BRK.B | T40: 84670702 | U40: US0846707026 | V40: 2073390 | W40: jrp group plc | X40: General Reinsurance AG (London branch), | Y40: Reinsurers | AI40: 43958
A41: SUPPLIER | B41: =C41&IF(U41="",R41,U41) -> GB00BCRX1J15US0846707026 | C41: GB00BCRX1J15 | D41: =SIGN(VLOOKUP(C41,has_scf!$E$2:$F$1366,2,FALSE)) -> 0 | E41: 43958 | F41: SUPPL-115039199 | G41: 89242004 | H41: 1319 | K41: Y | M41: General Reinsurance AG (London branch) | N41: Just Group Plc | O41: JUST | P41: G9331B109 | Q41: BCRX1J1 | R41: Berkshire Hathaway, Inc. | S41: BRK.B | T41: 84670702 | U41: US0846707026 | V41: 2073390 | W41: jrp group plc | X41: General Reinsurance AG (London branch), | Y41: Reinsurers | AI41: 43958
A42: SUPPLIER | B42: =C42&IF(U42="",R42,U42) -> GB0000353929CQS Cayman LP | C42: GB0000353929 | D42: =SIGN(VLOOKUP(C42,has_scf!$E$2:$F$1366,2,FALSE)) -> 0 | E42: 43089 | F42: SUPPL-118191551 | G42: 1921569 | H42: 9001091 | K42: Y | M42: CQS (UK) LLP | N42: CQS Natural Resources Growth & Income Plc | O42: CYN | P42: G2166J107 | Q42: 35392 | R42: CQS Cayman LP | W42: City Natural Resources High Yield | X42: CQS (UK) | Y42: investment manager | AI42: 45405
A43: SUPPLIER | B43: =C43&IF(U43="",R43,U43) -> GB00B7TW1V39US24703L2025 | C43: GB00B7TW1V39 | D43: =SIGN(VLOOKUP(C43,has_scf!$E$2:$F$1366,2,FALSE)) -> 1 | E43: 43416 | F43: SUPPL-115147572 | G43: 194535729 | H43: 6068620 | K43: Y | M43: Dell EMC Inc. | N43: Redcentric Plc | O43: RCN | P43: G7444T108 | Q43: B7TW1V3 | R43: Dell Technologies, Inc. | S43: DELL | T43: 24703L202 | U43: US24703L2025 | V43: BHKD3S6 | W43: redcentric plc | X43: Dell Technologies | Y43: Technology Partner | AI43: 44424
A44: SUPPLIER | B44: =C44&IF(U44="",R44,U44) -> GB00B7TW1V39US42824C1099 | C44: GB00B7TW1V39 | D44: =SIGN(VLOOKUP(C44,has_scf!$E$2:$F$1366,2,FALSE)) -> 1 | E44: 43416 | F44: SUPPL-115148050 | G44: 194535729 | H44: 76559657 | K44: Y | N44: Redcentric Plc | O44: RCN | P44: G7444T108 | Q44: B7TW1V3 | R44: Hewlett Packard Enterprise Co. | S44: HPE | T44: 42824C109 | U44: US42824C1099 | V44: BYVYWS0 | W44: redcentric plc | X44: Hewlett Packard Enterprise | Y44: solution | AI44: 767011
A45: SUPPLIER | B45: =C45&IF(U45="",R45,U45) -> GB00B7TW1V39US17275R1023 | C45: GB00B7TW1V39 | D45: =SIGN(VLOOKUP(C45,has_scf!$E$2:$F$1366,2,FALSE)) -> 1 | E45: 43416 | F45: SUPPL-115149536 | G45: 194535729 | H45: 2283 | K45: Y | M45: Lancope Inc. | N45: Redcentric Plc | O45: RCN | P45: G7444T108 | Q45: B7TW1V3 | R45: Cisco Systems, Inc. | S45: CSCO | T45: 17275R102 | U45: US17275R1023 | V45: 2198163 | W45: redcentric plc | X45: Lancope | Y45: Network Performance & Security Monitoring | AI45: 44069
A46: SUPPLIER | B46: =C46&IF(U46="",R46,U46) -> GB00B7TW1V39US17275R1023 | C46: GB00B7TW1V39 | D46: =SIGN(VLOOKUP(C46,has_scf!$E$2:$F$1366,2,FALSE)) -> 1 | E46: 44069 | F46: SUPPL-115149536 | G46: 194535729 | H46: 2283 | K46: Y | M46: Lancope Inc. | N46: Redcentric Plc | O46: RCN | P46: G7444T108 | Q46: B7TW1V3 | R46: Cisco Systems, Inc. | S46: CSCO | T46: 17275R102 | U46: US17275R1023 | V46: 2198163 | W46: redcentric plc | X46: Lancope | Y46: Network Performance & Security Monitoring | AI46: 44069
A47: SUPPLIER | B47: =C47&IF(U47="",R47,U47) -> GB00B7TW1V39US7685731074 | C47: GB00B7TW1V39 | D47: =SIGN(VLOOKUP(C47,has_scf!$E$2:$F$1366,2,FALSE)) -> 1 | E47: 43416 | F47: SUPPL-115150585 | G47: 194535729 | H47: 1810710 | K47: Y | N47: Redcentric Plc | O47: RCN | P47: G7444T108 | Q47: B7TW1V3 | R47: Riverbed Technology LLC | S47: RVBD | T47: 768573107 | U47: US7685731074 | V47: B1FH886 | W47: redcentric plc | X47: Riverbed | Y47: WAN Optimisation | AI47: 44069
A48: SUPPLIER | B48: =C48&IF(U48="",R48,U48) -> GB00B7TW1V39US7685731074 | C48: GB00B7TW1V39 | D48: =SIGN(VLOOKUP(C48,has_scf!$E$2:$F$1366,2,FALSE)) -> 1 | E48: 44069 | F48: SUPPL-115150585 | G48: 194535729 | H48: 1810710 | K48: Y | N48: Redcentric Plc | O48: RCN | P48: G7444T108 | Q48: B7TW1V3 | R48: Riverbed Technology LLC | S48: RVBD | T48: 768573107 | U48: US7685731074 | V48: B1FH886 | W48: redcentric plc | X48: Riverbed | Y48: WAN Optimisation | AI48: 44069
A49: SUPPLIER | B49: =C49&IF(U49="",R49,U49) -> GB00B012TP20TW0009921007 | C49: GB00B012TP20 | D49: =SIGN(VLOOKUP(C49,has_scf!$E$2:$F$1366,2,FALSE)) -> 0 | E49: 43033 | F49: SUPPL-115221590 | G49: 1832300 | H49: 22439618 | K49: Y | N49: Halfords Group Plc | O49: HFD | P49: G4280E105 | Q49: B012TP2 | R49: Giant Manufacturing Co., Ltd. | S49: 9921 | T49: Y2708Z106 | U49: TW0009921007 | V49: 6372167 | W49: Halfords Group | X49: Giant | AI49: 44468
A50: SUPPLIER | B50: =C50&IF(U50="",R50,U50) -> GB00B012TP20Specialized Bicycle Components, Inc. | C50: GB00B012TP20 | D50: =SIGN(VLOOKUP(C50,has_scf!$E$2:$F$1366,2,FALSE)) -> 0 | E50: 43033 | F50: SUPPL-115221640 | G50: 1832300 | H50: 1851751 | K50: Y | N50: Halfords Group Plc | O50: HFD | P50: G4280E105 | Q50: B012TP2 | R50: Specialized Bicycle Components, Inc. | W50: Halfords Group | X50: Specialized Bicycle | AI50: 44468
A51: SUPPLIER | B51: =C51&IF(U51="",R51,U51) -> GB00B012TP20Pending System GmbH & Co. KG | C51: GB00B012TP20 | D51: =SIGN(VLOOKUP(C51,has_scf!$E$2:$F$1366,2,FALSE)) -> 0 | E51: 43390 | F51: SUPPL-115221768 | G51: 1832300 | H51: 6445402 | K51: Y | N51: Halfords Group Plc | O51: HFD | P51: G4280E105 | Q51: B012TP2 | R51: Pending System GmbH & Co. KG | W51: Halfords Group | X51: CUBE | AI51: 44468
A52: SUPPLIER | B52: =C52&IF(U52="",R52,U52) -> GB0008052507GB00BF8Q6K64 | C52: GB0008052507 | D52: =SIGN(VLOOKUP(C52,has_scf!$E$2:$F$1366,2,FALSE)) -> 0 | E52: 43335 | F52: SUPPL-115268361 | G52: 1921512 | H52: 1758728 | K52: Y | M52: Aberdeen Fund Managers Limited | N52: Shires Income Plc | O52: SHRS | P52: G81096102 | Q52: 805250 | R52: Aberdeen Group Plc | S52: ABDN | T52: G0152L102 | U52: GB00BF8Q6K64 | V52: BF8Q6K6 | W52: Shires Income | X52: Aberdeen Standard Fund Managers | Y52: Alternative Investment Fund Manager | AI52: 44123
A53: SUPPLIER | B53: =C53&IF(U53="",R53,U53) -> GB0008052507GB00BF8Q6K64 | C53: GB0008052507 | D53: =SIGN(VLOOKUP(C53,has_scf!$E$2:$F$1366,2,FALSE)) -> 0 | E53: 44123 | F53: SUPPL-115268361 | G53: 1921512 | H53: 1758728 | K53: Y | M53: Aberdeen Standard Fund Managers Ltd | N53: Shires Income Plc | O53: SHRS | P53: G81096102 | Q53: 805250 | R53: Aberdeen Group Plc | S53: ABDN | T53: G0152L102 | U53: GB00BF8Q6K64 | V53: BF8Q6K6 | W53: Shires Income | X53: Aberdeen Standard Fund Managers | Y53: Alternative Investment Fund Manager | AI53: 45405
A54: SUPPLIER | B54: =C54&IF(U54="",R54,U54) -> GB0008481250US60935Y2081 | C54: GB0008481250 | D54: =SIGN(VLOOKUP(C54,has_scf!$E$2:$F$1366,2,FALSE)) -> 0 | E54: 43035 | F54: SUPPL-115339918 | G54: 1832428 | H54: 1734565 | K54: Y | N54: ME Group International Plc | O54: MEGP | P54: G70695112 | Q54: 848125 | R54: MoneyGram International, Inc. | S54: MGI | T54: 60935Y208 | U54: US60935Y2081 | V54: B4L5089 | W54: Photo-Me International | X54: MoneyGram | Y54: money transfer services | AI54: 44363
A55: SUPPLIER | B55: =C55&IF(U55="",R55,U55) -> GB00B196F554Consorzio ATR GIE | C55: GB00B196F554 | D55: =SIGN(VLOOKUP(C55,has_scf!$E$2:$F$1366,2,FALSE)) -> 0 | E55: 43035 | F55: SUPPL-115340969 | G55: 194524194 | H55: 8308931 | K55: Y | N55: Avation Plc | O55: AVAP | P55: G0713X108 | Q55: B196F55 | R55: Consorzio ATR GIE | W55: Avation | X55: ATR | Y55: 72-600 model | AI55: 767011
A56: SUPPLIER | B56: =C56&IF(U56="",R56,U56) -> GB00B196F554NL0000235190 | C56: GB00B196F554 | D56: =SIGN(VLOOKUP(C56,has_scf!$E$2:$F$1366,2,FALSE)) -> 0 | E56: 43035 | F56: SUPPL-115340999 | G56: 194524194 | H56: 1538921 | K56: Y | N56: Avation Plc | O56: AVAP | P56: G0713X108 | Q56: B196F55 | R56: Airbus SE | S56: AIR | T56: N0280G100 | U56: NL0000235190 | V56: 4012250 | W56: Avation | X56: Airbus | Y56: A320/A321 | Z56: A220 | AI56: 767011
A57: SUPPLIER | B57: =C57&IF(U57="",R57,U57) -> GB00BYSXWW41KR7005930003 | C57: GB00BYSXWW41 | D57: =SIGN(VLOOKUP(C57,has_scf!$E$2:$F$1366,2,FALSE)) -> 0 | E57: 43038 | F57: SUPPL-115402661 | G57: 6816443 | H57: 1835724 | K57: Y | N57: Midwich Group Plc | O57: MIDW | P57: G6113M105 | Q57: BYSXWW4 | R57: Samsung Electronics Co., Ltd. | S57: 5930 | T57: Y74718100 | U57: KR7005930003 | V57: 6771720 | W57: MIDWICH GROUP | X57: Samsung Electronics | Y57: AV products | AI57: 767011
A58: SUPPLIER | B58: =C58&IF(U58="",R58,U58) -> GB00BYSXWW41KR7066570003 | C58: GB00BYSXWW41 | D58: =SIGN(VLOOKUP(C58,has_scf!$E$2:$F$1366,2,FALSE)) -> 0 | E58: 43038 | F58: SUPPL-115403013 | G58: 6816443 | H58: 230298 | K58: Y | N58: Midwich Group Plc | O58: MIDW | P58: G6113M105 | Q58: BYSXWW4 | R58: LG Electronics, Inc. | S58: 66570 | T58: Y5275H177 | U58: KR7066570003 | V58: 6520739 | W58: MIDWICH GROUP | X58: LG Electronics | Y58: AV products | AI58: 44779
A59: SUPPLIER | B59: =C59&IF(U59="",R59,U59) -> GB00BYSXWW41JP3414750004 | C59: GB00BYSXWW41 | D59: =SIGN(VLOOKUP(C59,has_scf!$E$2:$F$1366,2,FALSE)) -> 0 | E59: 43038 | F59: SUPPL-115403031 | G59: 6816443 | H59: 1914537 | K59: Y | N59: Midwich Group Plc | O59: MIDW | P59: G6113M105 | Q59: BYSXWW4 | R59: Seiko Epson Corp. | S59: 6724 | T59: J7030F105 | U59: JP3414750004 | V59: 6616508 | W59: MIDWICH GROUP | X59: Epson | Y59: AV products | AI59: 767011
A60: SUPPLIER | B60: =C60&IF(U60="",R60,U60) -> GB00BYSXWW41JP3733000008 | C60: GB00BYSXWW41 | D60: =SIGN(VLOOKUP(C60,has_scf!$E$2:$F$1366,2,FALSE)) -> 0 | E60: 43038 | F60: SUPPL-115403054 | G60: 6816443 | H60: 7161 | K60: Y | N60: Midwich Group Plc | O60: MIDW | P60: G6113M105 | Q60: BYSXWW4 | R60: NEC Corp. | S60: 6701 | T60: J48818207 | U60: JP3733000008 | V60: 6640400 | W60: MIDWICH GROUP | X60: NEC | Y60: AV products | AI60: 44957
A61: SUPPLIER | B61: =C61&IF(U61="",R61,U61) -> GB00BYSXWW41 | C61: GB00BYSXWW41 | D61: =SIGN(VLOOKUP(C61,has_scf!$E$2:$F$1366,2,FALSE)) -> 0 | E61: 43038 | F61: SUPPL-115411645 | G61: 6816443 | H61: 105711859 | K61: Y | N61: Midwich Group Plc | O61: MIDW | P61: G6113M105 | Q61: BYSXWW4 | W61: MIDWICH GROUP | X61: d p d uk | Y61: Logistics | AI61: 44958
A62: SUPPLIER | B62: =C62&IF(U62="",R62,U62) -> GB00BYSXWW41GB00B17WCR61 | C62: GB00BYSXWW41 | D62: =SIGN(VLOOKUP(C62,has_scf!$E$2:$F$1366,2,FALSE)) -> 0 | E62: 43038 | F62: SUPPL-115411664 | G62: 6816443 | H62: 1832415 | K62: Y | M62: Tuffnells Parcels Express Ltd. | N62: Midwich Group Plc | O62: MIDW | P62: G6113M105 | Q62: BYSXWW4 | R62: Smiths News Plc | S62: SNWS | T62: G8250W102 | U62: GB00B17WCR61 | V62: B17WCR6 | W62: MIDWICH GROUP | X62: Tuffnells Parcels Express | Y62: Logistics | AI62: 45051
A63: SUPPLIER | B63: =C63&IF(U63="",R63,U63) -> GB00BYSXWW41DK0060079531 | C63: GB00BYSXWW41 | D63: =SIGN(VLOOKUP(C63,has_scf!$E$2:$F$1366,2,FALSE)) -> 0 | E63: 43671 | F63: SUPPL-115411710 | G63: 6816443 | H63: 22449199 | K63: Y | M63: Palletline Ltd. | N63: Midwich Group Plc | O63: MIDW | P63: G6113M105 | Q63: BYSXWW4 | R63: DSV A/S | S63: DSV | T63: K31864117 | U63: DK0060079531 | V63: B1WT5G2 | W63: MIDWICH GROUP | X63: Palletline | Y63: Logistics | AI63: 45051
A64: SUPPLIER | B64: =C64&IF(U64="",R64,U64) -> GB00BYSXWW41US88554D2053 | C64: GB00BYSXWW41 | D64: =SIGN(VLOOKUP(C64,has_scf!$E$2:$F$1366,2,FALSE)) -> 0 | E64: 43038 | F64: SUPPL-115415311 | G64: 6816443 | H64: 18 | K64: Y | N64: Midwich Group Plc | O64: MIDW | P64: G6113M105 | Q64: BYSXWW4 | R64: 3D Systems Corp. | S64: DDD | T64: 88554D205 | U64: US88554D2053 | V64: 2889768 | W64: MIDWICH GROUP | X64: 3D Systems | Y64: AV Products | AI64: 44780
A65: SUPPLIER | B65: =C65&IF(U65="",R65,U65) -> GB00BYSXWW41 | C65: GB00BYSXWW41 | D65: =SIGN(VLOOKUP(C65,has_scf!$E$2:$F$1366,2,FALSE)) -> 0 | E65: 43038 | F65: SUPPL-115416994 | G65: 6816443 | H65: 9160420 | K65: Y | M65: Atlona Technologies, Inc. | N65: Midwich Group Plc | O65: MIDW | P65: G6113M105 | Q65: BYSXWW4 | W65: MIDWICH GROUP | Y65: AV products | AI65: 45051
A66: SUPPLIER | B66: =C66&IF(U66="",R66,U66) -> GB00BYSXWW41NL0000009538 | C66: GB00BYSXWW41 | D66: =SIGN(VLOOKUP(C66,has_scf!$E$2:$F$1366,2,FALSE)) -> 0 | E66: 43038 | F66: SUPPL-115417337 | G66: 6816443 | H66: 71738715 | K66: Y | N66: Midwich Group Plc | O66: MIDW | P66: G6113M105 | Q66: BYSXWW4 | R66: Koninklijke Philips NV | S66: PHIA | T66: N7637U112 | U66: NL0000009538 | V66: 5986622 | W66: MIDWICH GROUP | X66: Philips | Y66: Philips Dictation | AI66: 44957
A67: SUPPLIER | B67: =C67&IF(U67="",R67,U67) -> GB00BYSXWW41JP3359600008 | C67: GB00BYSXWW41 | D67: =SIGN(VLOOKUP(C67,has_scf!$E$2:$F$1366,2,FALSE)) -> 0 | E67: 43038 | F67: SUPPL-115417680 | G67: 6816443 | H67: 12013 | K67: Y | N67: Midwich Group Plc | O67: MIDW | P67: G6113M105 | Q67: BYSXWW4 | R67: Sharp Corp. | S67: 6753 | T67: J71434112 | U67: JP3359600008 | V67: 6800602 | W67: MIDWICH GROUP | X67: Sharp | Y67: AV Products | AI67: 767011
A68: SUPPLIER | B68: =C68&IF(U68="",R68,U68) -> GB00BYSXWW41TW0003565008 | C68: GB00BYSXWW41 | D68: =SIGN(VLOOKUP(C68,has_scf!$E$2:$F$1366,2,FALSE)) -> 0 | E68: 43038 | F68: SUPPL-115417732 | G68: 6816443 | H68: 22434018 | K68: Y | N68: Midwich Group Plc | O68: MIDW | P68: G6113M105 | Q68: BYSXWW4 | R68: Optoma Corp. | S68: 3565 | T68: Y6496A108 | U68: TW0003565008 | V68: B231NQ0 | W68: MIDWICH GROUP | Y68: AV Products | AI68: 44957
A69: SUPPLIER | B69: =C69&IF(U69="",R69,U69) -> GB00BYSXWW41Bennett International Group LLC | C69: GB00BYSXWW41 | D69: =SIGN(VLOOKUP(C69,has_scf!$E$2:$F$1366,2,FALSE)) -> 0 | E69: 43038 | F69: SUPPL-115417799 | G69: 6816443 | H69: 8317426 | K69: Y | M69: B-Tech International Ltd. | N69: Midwich Group Plc | O69: MIDW | P69: G6113M105 | Q69: BYSXWW4 | R69: Bennett International Group LLC | W69: MIDWICH GROUP | X69: B-Tech International | Y69: AV Products | AI69: 767011
A70: SUPPLIER | B70: =C70&IF(U70="",R70,U70) -> GB00BYSXWW41BE0974362940 | C70: GB00BYSXWW41 | D70: =SIGN(VLOOKUP(C70,has_scf!$E$2:$F$1366,2,FALSE)) -> 0 | E70: 43038 | F70: SUPPL-115417922 | G70: 6816443 | H70: 245108 | K70: Y | N70: Midwich Group Plc | O70: MIDW | P70: G6113M105 | Q70: BYSXWW4 | R70: Barco NV | S70: BAR | T70: B0833G105 | U70: BE0974362940 | V70: BMB3BN1 | W70: MIDWICH GROUP | X70: Barco | Y70: AV Products | AI70: 767011
A71: SUPPLIER | B71: =C71&IF(U71="",R71,U71) -> GB00BYSXWW41JP3818000006 | C71: GB00BYSXWW41 | D71: =SIGN(VLOOKUP(C71,has_scf!$E$2:$F$1366,2,FALSE)) -> 0 | E71: 43038 | F71: SUPPL-115418045 | G71: 6816443 | H71: 11424 | K71: Y | N71: Midwich Group Plc | O71: MIDW | P71: G6113M105 | Q71: BYSXWW4 | R71: Fujitsu Ltd. | S71: 6702 | T71: J15708159 | U71: JP3818000006 | V71: 6356945 | W71: MIDWICH GROUP | X71: Fujitsu | Y71: AV Solutions | AI71: 767011
A72: SUPPLIER | B72: =C72&IF(U72="",R72,U72) -> GG00BSWT8V72US43300A2033 | C72: GG00BSWT8V72 | D72: =SIGN(VLOOKUP(C72,has_scf!$E$2:$F$1366,2,FALSE)) -> 0 | E72: 43451 | F72: SUPPL-115517527 | G72: 194510146 | H72: 1889493 | K72: Y | M72: Waldorf Astoria Management LLC | N72: DCI Advisors Ltd. | O72: DCI | P72: G2696V109 | Q72: BSWT8V7 | R72: Hilton Worldwide Holdings, Inc. | S72: HLT | T72: 43300A203 | U72: US43300A2033 | V72: BYVMW06 | W72: DOLHF | X72: Waldorf Astoria | Y72: Hotel operator | AI72: 44778
A73: SUPPLIER | B73: =C73&IF(U73="",R73,U73) -> GG00BSWT8V72Oberoi Group of Hotels | C73: GG00BSWT8V72 | D73: =SIGN(VLOOKUP(C73,has_scf!$E$2:$F$1366,2,FALSE)) -> 0 | E73: 43041 | F73: SUPPL-115517550 | G73: 194510146 | H73: 30002701 | K73: Y | N73: DCI Advisors Ltd. | O73: DCI | P73: G2696V109 | Q73: BSWT8V7 | R73: Oberoi Group of Hotels | W73: DOLHF | X73: The Oberoi Group | Y73: Hotel operator | AI73: 767011
A74: SUPPLIER | B74: =C74&IF(U74="",R74,U74) -> GB00BBM56V29GB00BF8Q6K64 | C74: GB00BBM56V29 | D74: =SIGN(VLOOKUP(C74,has_scf!$E$2:$F$1366,2,FALSE)) -> 0 | E74: 43372 | F74: SUPPL-115564230 | G74: 1921590 | H74: 1758728 | K74: Y | M74: Aberdeen Fund Managers Limited | N74: abrdn New Dawn Investment Trust plc | O74: ABD | P74: G0059Q162 | Q74: BBM56V2 | R74: Aberdeen Group Plc | S74: ABDN | T74: G0152L102 | U74: GB00BF8Q6K64 | V74: BF8Q6K6 | W74: Aberdeen New Dawn | X74: Aberdeen Fund Managers Limited | Y74: AIFM | Z74: Manager | AA74: Alternative Investment Fund Manager | AI74: 45405
A75: SUPPLIER | B75: =C75&IF(U75="",R75,U75) -> GB00B7N0K053Hovis Holdings Ltd. | C75: GB00B7N0K053 | D75: =SIGN(VLOOKUP(C75,has_scf!$E$2:$F$1366,2,FALSE)) -> 0 | E75: 43712 | F75: SUPPL-115576152 | G75: 1832425 | H75: 16029675 | K75: Y | M75: Hovis Ltd. | N75: Premier Foods Plc | O75: PFD | P75: G7S17N124 | Q75: B7N0K05 | R75: Hovis Holdings Ltd. | W75: Premier Foods | AI75: 44039
A76: SUPPLIER | B76: =C76&IF(U76="",R76,U76) -> GB00B7N0K053Hovis Holdings Ltd. | C76: GB00B7N0K053 | D76: =SIGN(VLOOKUP(C76,has_scf!$E$2:$F$1366,2,FALSE)) -> 0 | E76: 44039 | F76: SUPPL-115576152 | G76: 1832425 | H76: 16029675 | K76: Y | M76: Hovis Ltd. | N76: Premier Foods Plc | O76: PFD | P76: G7S17N124 | Q76: B7N0K05 | R76: Hovis Holdings Ltd. | W76: Premier Foods | AI76: 44039
A77: SUPPLIER | B77: =C77&IF(U77="",R77,U77) -> GB00BYSXWW41Analog Way SAS | C77: GB00BYSXWW41 | D77: =SIGN(VLOOKUP(C77,has_scf!$E$2:$F$1366,2,FALSE)) -> 0 | E77: 43045 | F77: SUPPL-115614048 | G77: 6816443 | H77: 100826870 | K77: Y | N77: Midwich Group Plc | O77: MIDW | P77: G6113M105 | Q77: BYSXWW4 | R77: Analog Way SAS | W77: MIDWICH GROUP | X77: analog way sas | Y77: AV Products | AI77: 44957
A78: SUPPLIER | B78: =C78&IF(U78="",R78,U78) -> GB00BYSXWW41 | C78: GB00BYSXWW41 | D78: =SIGN(VLOOKUP(C78,has_scf!$E$2:$F$1366,2,FALSE)) -> 0 | E78: 43045 | F78: SUPPL-115614152 | G78: 6816443 | H78: 9306709 | K78: Y | N78: Midwich Group Plc | O78: MIDW | P78: G6113M105 | Q78: BYSXWW4 | W78: MIDWICH GROUP | Y78: AV Products | AI78: 45768
A79: SUPPLIER | B79: =C79&IF(U79="",R79,U79) -> GB00BYSXWW41CNE100001CB7 | C79: GB00BYSXWW41 | D79: =SIGN(VLOOKUP(C79,has_scf!$E$2:$F$1366,2,FALSE)) -> 0 | E79: 43045 | F79: SUPPL-115614206 | G79: 6816443 | H79: 194530338 | K79: Y | M79: Planar Systems, Inc. | N79: Midwich Group Plc | O79: MIDW | P79: G6113M105 | Q79: BYSXWW4 | R79: Leyard Optoelectronic Co., Ltd. | S79: 300296 | T79: Y5171W104 | U79: CNE100001CB7 | V79: B71R6P5 | W79: MIDWICH GROUP | X79: Planar Systems | Y79: AV Products | AI79: 44957
A80: SUPPLIER | B80: =C80&IF(U80="",R80,U80) -> GB00BYSXWW41JP3209000003 | C80: GB00BYSXWW41 | D80: =SIGN(VLOOKUP(C80,has_scf!$E$2:$F$1366,2,FALSE)) -> 0 | E80: 43045 | F80: SUPPL-115614250 | G80: 6816443 | H80: 11587 | K80: Y | N80: Midwich Group Plc | O80: MIDW | P80: G6113M105 | Q80: BYSXWW4 | R80: Casio Computer Co., Ltd. | S80: 6952 | T80: J05250139 | U80: JP3209000003 | V80: 6178967 | W80: MIDWICH GROUP | X80: Casio | Y80: AV Products | AI80: 44957
A81: SUPPLIER | B81: =C81&IF(U81="",R81,U81) -> GB00BYSXWW41JP3973400009 | C81: GB00BYSXWW41 | D81: =SIGN(VLOOKUP(C81,has_scf!$E$2:$F$1366,2,FALSE)) -> 0 | E81: 43045 | F81: SUPPL-115614290 | G81: 6816443 | H81: 11599 | K81: Y | N81: Midwich Group Plc | O81: MIDW | P81: G6113M105 | Q81: BYSXWW4 | R81: Ricoh Co., Ltd. | S81: 7752 | T81: J64683105 | U81: JP3973400009 | V81: 6738220 | W81: MIDWICH GROUP | X81: Ricoh | Y81: AV Products | AI81: 767011
A82: SUPPLIER | B82: =C82&IF(U82="",R82,U82) -> GB00BYSXWW41 | C82: GB00BYSXWW41 | D82: =SIGN(VLOOKUP(C82,has_scf!$E$2:$F$1366,2,FALSE)) -> 0 | E82: 43045 | F82: SUPPL-115614308 | G82: 6816443 | H82: 8696817 | K82: Y | N82: Midwich Group Plc | O82: MIDW | P82: G6113M105 | Q82: BYSXWW4 | W82: MIDWICH GROUP | X82: TV One | Y82: AV Products | AI82: 45442
A83: SUPPLIER | B83: =C83&IF(U83="",R83,U83) -> GB00BYSXWW41JP3435000009 | C83: GB00BYSXWW41 | D83: =SIGN(VLOOKUP(C83,has_scf!$E$2:$F$1366,2,FALSE)) -> 0 | E83: 43045 | F83: SUPPL-115614394 | G83: 6816443 | H83: 9425 | K83: Y | N83: Midwich Group Plc | O83: MIDW | P83: G6113M105 | Q83: BYSXWW4 | R83: Sony Group Corp. | S83: 6758 | T83: J76379106 | U83: JP3435000009 | V83: 6821506 | W83: MIDWICH GROUP | X83: Sony | Y83: AV Products | AI83: 767011
A84: SUPPLIER | B84: =C84&IF(U84="",R84,U84) -> GB00BYSXWW41 | C84: GB00BYSXWW41 | D84: =SIGN(VLOOKUP(C84,has_scf!$E$2:$F$1366,2,FALSE)) -> 0 | E84: 43045 | F84: SUPPL-115614412 | G84: 6816443 | H84: 1533046 | K84: Y | N84: Midwich Group Plc | O84: MIDW | P84: G6113M105 | Q84: BYSXWW4 | W84: MIDWICH GROUP | X84: Eizo | Y84: AV Products | AI84: 44958
A85: SUPPLIER | B85: =C85&IF(U85="",R85,U85) -> GB00BYSXWW41JP3242800005 | C85: GB00BYSXWW41 | D85: =SIGN(VLOOKUP(C85,has_scf!$E$2:$F$1366,2,FALSE)) -> 0 | E85: 43045 | F85: SUPPL-115614433 | G85: 6816443 | H85: 1811 | K85: Y | N85: Midwich Group Plc | O85: MIDW | P85: G6113M105 | Q85: BYSXWW4 | R85: Canon, Inc. | S85: 7751 | T85: J05124144 | U85: JP3242800005 | V85: 6172323 | W85: MIDWICH GROUP | X85: Canon | Y85: AV Products | AI85: 767011
A86: SUPPLIER | B86: =C86&IF(U86="",R86,U86) -> GB00BYSXWW41JP3788600009 | C86: GB00BYSXWW41 | D86: =SIGN(VLOOKUP(C86,has_scf!$E$2:$F$1366,2,FALSE)) -> 0 | E86: 43045 | F86: SUPPL-115614451 | G86: 6816443 | H86: 5002 | K86: Y | N86: Midwich Group Plc | O86: MIDW | P86: G6113M105 | Q86: BYSXWW4 | R86: Hitachi Ltd. | S86: 6501 | T86: J20454112 | U86: JP3788600009 | V86: 6429104 | W86: MIDWICH GROUP | X86: Hitachi | Y86: AV Products | AI86: 44779
A87: SUPPLIER | B87: =C87&IF(U87="",R87,U87) -> GB00BYSXWW41TW0008215005 | C87: GB00BYSXWW41 | D87: =SIGN(VLOOKUP(C87,has_scf!$E$2:$F$1366,2,FALSE)) -> 0 | E87: 43045 | F87: SUPPL-115614469 | G87: 6816443 | H87: 22444694 | K87: Y | N87: Midwich Group Plc | O87: MIDW | P87: G6113M105 | Q87: BYSXWW4 | R87: BenQ Materials Corp. | S87: 8215 | T87: Y2022D104 | U87: TW0008215005 | V87: 6694162 | W87: MIDWICH GROUP | X87: BenQ Materials | Y87: AV Products | AI87: 45051
A88: SUPPLIER | B88: =C88&IF(U88="",R88,U88) -> GB00B3W40C23CA82509L1076 | C88: GB00B3W40C23 | D88: =SIGN(VLOOKUP(C88,has_scf!$E$2:$F$1366,2,FALSE)) -> 0 | E88: 43441 | F88: SUPPL-118605645 | G88: 194527201 | H88: 7372627 | K88: Y | N88: Dotdigital Group Plc | O88: DOTD | P88: G2897D106 | Q88: B3W40C2 | R88: Shopify, Inc. | S88: SHOP | T88: 82509L107 | U88: CA82509L1076 | V88: BX865C7 | W88: Dotdigital | X88: Shopify | Y88: Engagement Cloud | AI88: 45639
A89: SUPPLIER | B89: =C89&IF(U89="",R89,U89) -> GB0002258472M&M Investment Co. Ltd. | C89: GB0002258472 | D89: =SIGN(VLOOKUP(C89,has_scf!$E$2:$F$1366,2,FALSE)) -> 0 | E89: 43766 | F89: SUPPL-118612798 | G89: 1921749 | H89: 90743110 | K89: Y | M89: M & L Capital Management | N89: Manchester & London Investment Trust Plc | O89: MNL | P89: G57764105 | Q89: 225847 | R89: M&M Investment Co. Ltd. | W89: Manchester & London | X89: mm investment plc | Y89: substantial shareholdings, investment management | AI89: 44148
A90: SUPPLIER | B90: =C90&IF(U90="",R90,U90) -> GB0002258472M&M Investment Co. Ltd. | C90: GB0002258472 | D90: =SIGN(VLOOKUP(C90,has_scf!$E$2:$F$1366,2,FALSE)) -> 0 | E90: 44148 | F90: SUPPL-118612798 | G90: 1921749 | H90: 90743110 | K90: Y | M90: M & L Capital Management | N90: Manchester & London Investment Trust Plc | O90: MNL | P90: G57764105 | Q90: 225847 | R90: M&M Investment Co. Ltd. | W90: Manchester & London | X90: mm investment plc | Y90: substantial shareholdings, investment management | AI90: 44148
A91: SUPPLIER | B91: =C91&IF(U91="",R91,U91) -> GB00BYZDVK82US0231351067 | C91: GB00BYZDVK82 | D91: =SIGN(VLOOKUP(C91,has_scf!$E$2:$F$1366,2,FALSE)) -> 1 | E91: 43111 | F91: SUPPL-119050230 | G91: 7837357 | H91: 441 | K91: Y | M91: Amazon Web Services | N91: Softcat Plc | O91: SCT | P91: G8251T108 | Q91: BYZDVK8 | R91: Amazon.com, Inc. | S91: AMZN | T91: 23135106 | U91: US0231351067 | V91: 2000019 | W91: Softcat | X91: Amazon Web Services | Y91: Cloud | Z91: Public Cloud | AA91: Migration | AB91: DevOps | AC91: Storage | AD91: AWS Marketplace | AI91: 45617
A92: SUPPLIER | B92: =C92&IF(U92="",R92,U92) -> GB00BYZDVK82US0683231049 | C92: GB00BYZDVK82 | D92: =SIGN(VLOOKUP(C92,has_scf!$E$2:$F$1366,2,FALSE)) -> 1 | E92: 43111 | F92: SUPPL-119050604 | G92: 7837357 | H92: 1846648 | K92: Y | N92: Softcat Plc | O92: SCT | P92: G8251T108 | Q92: BYZDVK8 | R92: Barracuda Networks, Inc. | S92: CUDA | T92: 68323104 | U92: US0683231049 | V92: BFZCHY8 | W92: Softcat | X92: Barracuda Networks | AI92: 44959
A93: SUPPLIER | B93: =C93&IF(U93="",R93,U93) -> GB00BYZDVK82Cylance, Inc. | C93: GB00BYZDVK82 | D93: =SIGN(VLOOKUP(C93,has_scf!$E$2:$F$1366,2,FALSE)) -> 1 | E93: 43111 | F93: SUPPL-119050756 | G93: 7837357 | H93: 8420496 | K93: Y | N93: Softcat Plc | O93: SCT | P93: G8251T108 | Q93: BYZDVK8 | R93: Cylance, Inc. | W93: Softcat | X93: Cylance | Y93: hardware | Z93: software | AI93: 44605
A94: SUPPLIER | B94: =C94&IF(U94="",R94,U94) -> GB00BYZDVK82US9476841062 | C94: GB00BYZDVK82 | D94: =SIGN(VLOOKUP(C94,has_scf!$E$2:$F$1366,2,FALSE)) -> 1 | E94: 43111 | F94: SUPPL-119050928 | G94: 7837357 | H94: 222830 | K94: Y | N94: Softcat Plc | O94: SCT | P94: G8251T108 | Q94: BYZDVK8 | R94: Forcepoint LLC | S94: WBSN | T94: 947684106 | U94: US9476841062 | V94: 2569275 | W94: Softcat | X94: Websense | Y94: data | Z94: Data Protection | AA94: Cloud apps | AI94: 767011
A95: SUPPLIER | B95: =C95&IF(U95="",R95,U95) -> GB00BYZDVK82US34959E1091 | C95: GB00BYZDVK82 | D95: =SIGN(VLOOKUP(C95,has_scf!$E$2:$F$1366,2,FALSE)) -> 1 | E95: 43111 | F95: SUPPL-119051102 | G95: 7837357 | H95: 1675874 | K95: Y | N95: Softcat Plc | O95: SCT | P95: G8251T108 | Q95: BYZDVK8 | R95: Fortinet, Inc. | S95: FTNT | T95: 3.4959e+113 | U95: US34959E1091 | V95: B5B2106 | W95: Softcat | X95: Fortinet | AI95: 44959
A96: SUPPLIER | B96: =C96&IF(U96="",R96,U96) -> GB00BYZDVK82JP3818000006 | C96: GB00BYZDVK82 | D96: =SIGN(VLOOKUP(C96,has_scf!$E$2:$F$1366,2,FALSE)) -> 1 | E96: 43111 | F96: SUPPL-119051209 | G96: 7837357 | H96: 11424 | K96: Y | N96: Softcat Plc | O96: SCT | P96: G8251T108 | Q96: BYZDVK8 | R96: Fujitsu Ltd. | S96: 6702 | T96: J15708159 | U96: JP3818000006 | V96: 6356945 | W96: Softcat | X96: Fujitsu | AI96: 44959
A97: SUPPLIER | B97: =C97&IF(U97="",R97,U97) -> GB00BYZDVK82US4592001014 | C97: GB00BYZDVK82 | D97: =SIGN(VLOOKUP(C97,has_scf!$E$2:$F$1366,2,FALSE)) -> 1 | E97: 43111 | F97: SUPPL-119051406 | G97: 7837357 | H97: 5179 | K97: Y | N97: Softcat Plc | O97: SCT | P97: G8251T108 | Q97: BYZDVK8 | R97: International Business Machines Corp. | S97: IBM | T97: 459200101 | U97: US4592001014 | V97: 2005973 | W97: Softcat | X97: IBM | AI97: 44959
A98: SUPPLIER | B98: =C98&IF(U98="",R98,U98) -> GB00BYZDVK82Ivanti Software, Inc. | C98: GB00BYZDVK82 | D98: =SIGN(VLOOKUP(C98,has_scf!$E$2:$F$1366,2,FALSE)) -> 1 | E98: 43111 | F98: SUPPL-119051575 | G98: 7837357 | H98: 103600372 | K98: Y | N98: Softcat Plc | O98: SCT | P98: G8251T108 | Q98: BYZDVK8 | R98: Ivanti Software, Inc. | W98: Softcat | X98: ivanti software | AI98: 44959
A99: SUPPLIER | B99: =C99&IF(U99="",R99,U99) -> GB00BYZDVK82BRJ1NPBDR005 | C99: GB00BYZDVK82 | D99: =SIGN(VLOOKUP(C99,has_scf!$E$2:$F$1366,2,FALSE)) -> 1 | E99: 43111 | F99: SUPPL-119051678 | G99: 7837357 | H99: 218570 | K99: Y | N99: Softcat Plc | O99: SCT | P99: G8251T108 | Q99: BYZDVK8 | R99: Juniper Networks, Inc. | S99: J1NP34 | T99: FDSLET1K7 | U99: BRJ1NPBDR005 | V99: BK926G4 | W99: Softcat | X99: Juniper | Y99: hardware | Z99: software | AI99: 44605
A100: SUPPLIER | B100: =C100&IF(U100="",R100,U100) -> GB00BYZDVK82Kingston Technology Corp. | C100: GB00BYZDVK82 | D100: =SIGN(VLOOKUP(C100,has_scf!$E$2:$F$1366,2,FALSE)) -> 1 | E100: 43111 | F100: SUPPL-119051969 | G100: 7837357 | H100: 212700 | K100: Y | N100: Softcat Plc | O100: SCT | P100: G8251T108 | Q100: BYZDVK8 | R100: Kingston Technology Corp. | W100: Softcat | X100: Kingston | AI100: 44959
...

Sheet doublecounting
C2: in target customer relationship | D2: in source supplier relationships | E2: doublecounting | F2: in target with scf | G2: in source with scf | H2: doublecounting
B3: GB00BK9RKT01SE0000407991 | C3: =COUNTIF(target_uk!$B$2:$B$3030,doublecounting!B3) -> 2 | D3: =COUNTIF(source_uk!$B$2:$B$2603,doublecounting!B3) -> 0 | E3: =SIGN(C3*D3) -> 0 | F3: =COUNTIFS(target_uk!$B$2:$B$3030,doublecounting!B3,target_uk!$D$2:$D$3030,1) -> 2 | G3: =COUNTIFS(source_uk!$B$2:$B$2603,doublecounting!B3,source_uk!$D$2:$D$2603,1) -> 0 | H3: =SIGN(F3*G3) -> 0
B4: GB00B3MBS747US84763R1014 | C4: =COUNTIF(target_uk!$B$2:$B$3030,doublecounting!B4) -> 1 | D4: =COUNTIF(source_uk!$B$2:$B$2603,doublecounting!B4) -> 0 | E4: =SIGN(C4*D4) -> 0 | F4: =COUNTIFS(target_uk!$B$2:$B$3030,doublecounting!B4,target_uk!$D$2:$D$3030,1) -> 0 | G4: =COUNTIFS(source_uk!$B$2:$B$2603,doublecounting!B4,source_uk!$D$2:$D$2603,1) -> 0 | H4: =SIGN(F4*G4) -> 0
B5: GB00B012TP20US84763R1014 | C5: =COUNTIF(target_uk!$B$2:$B$3030,doublecounting!B5) -> 1 | D5: =COUNTIF(source_uk!$B$2:$B$2603,doublecounting!B5) -> 0 | E5: =SIGN(C5*D5) -> 0 | F5: =COUNTIFS(target_uk!$B$2:$B$3030,doublecounting!B5,target_uk!$D$2:$D$3030,1) -> 0 | G5: =COUNTIFS(source_uk!$B$2:$B$2603,doublecounting!B5,source_uk!$D$2:$D$2603,1) -> 0 | H5: =SIGN(F5*G5) -> 0
B6: GB00BRJQ8J25GB0009422543 | C6: =COUNTIF(target_uk!$B$2:$B$3030,doublecounting!B6) -> 5 | D6: =COUNTIF(source_uk!$B$2:$B$2603,doublecounting!B6) -> 0 | E6: =SIGN(C6*D6) -> 0 | F6: =COUNTIFS(target_uk!$B$2:$B$3030,doublecounting!B6,target_uk!$D$2:$D$3030,1) -> 0 | G6: =COUNTIFS(source_uk!$B$2:$B$2603,doublecounting!B6,source_uk!$D$2:$D$2603,1) -> 0 | H6: =SIGN(F6*G6) -> 0
B7: GB00B0744B38US6097201072 | C7: =COUNTIF(target_uk!$B$2:$B$3030,doublecounting!B7) -> 3 | D7: =COUNTIF(source_uk!$B$2:$B$2603,doublecounting!B7) -> 0 | E7: =SIGN(C7*D7) -> 0 | F7: =COUNTIFS(target_uk!$B$2:$B$3030,doublecounting!B7,target_uk!$D$2:$D$3030,1) -> 0 | G7: =COUNTIFS(source_uk!$B$2:$B$2603,doublecounting!B7,source_uk!$D$2:$D$2603,1) -> 0 | H7: =SIGN(F7*G7) -> 0
B8: GB00B1L5QH97MT0000780107 | C8: =COUNTIF(target_uk!$B$2:$B$3030,doublecounting!B8) -> 2 | D8: =COUNTIF(source_uk!$B$2:$B$2603,doublecounting!B8) -> 0 | E8: =SIGN(C8*D8) -> 0 | F8: =COUNTIFS(target_uk!$B$2:$B$3030,doublecounting!B8,target_uk!$D$2:$D$3030,1) -> 0 | G8: =COUNTIFS(source_uk!$B$2:$B$2603,doublecounting!B8,source_uk!$D$2:$D$2603,1) -> 0 | H8: =SIGN(F8*G8) -> 0
B9: GB0031274896LK0080N00008 | C9: =COUNTIF(target_uk!$B$2:$B$3030,doublecounting!B9) -> 2 | D9: =COUNTIF(source_uk!$B$2:$B$2603,doublecounting!B9) -> 0 | E9: =SIGN(C9*D9) -> 0 | F9: =COUNTIFS(target_uk!$B$2:$B$3030,doublecounting!B9,target_uk!$D$2:$D$3030,1) -> 2 | G9: =COUNTIFS(source_uk!$B$2:$B$2603,doublecounting!B9,source_uk!$D$2:$D$2603,1) -> 0 | H9: =SIGN(F9*G9) -> 0
B10: GB0032089863LK0080N00008 | C10: =COUNTIF(target_uk!$B$2:$B$3030,doublecounting!B10) -> 2 | D10: =COUNTIF(source_uk!$B$2:$B$2603,doublecounting!B10) -> 0 | E10: =SIGN(C10*D10) -> 0 | F10: =COUNTIFS(target_uk!$B$2:$B$3030,doublecounting!B10,target_uk!$D$2:$D$3030,1) -> 0 | G10: =COUNTIFS(source_uk!$B$2:$B$2603,doublecounting!B10,source_uk!$D$2:$D$2603,1) -> 0 | H10: =SIGN(F10*G10) -> 0
B11: GB00B63H8491NO0003064107 | C11: =COUNTIF(target_uk!$B$2:$B$3030,doublecounting!B11) -> 1 | D11: =COUNTIF(source_uk!$B$2:$B$2603,doublecounting!B11) -> 0 | E11: =SIGN(C11*D11) -> 0 | F11: =COUNTIFS(target_uk!$B$2:$B$3030,doublecounting!B11,target_uk!$D$2:$D$3030,1) -> 1 | G11: =COUNTIFS(source_uk!$B$2:$B$2603,doublecounting!B11,source_uk!$D$2:$D$2603,1) -> 0 | H11: =SIGN(F11*G11) -> 0
B12: GB0007325078L. G. Balakrishnan & Brothers | C12: =COUNTIF(target_uk!$B$2:$B$3030,doublecounting!B12) -> 2 | D12: =COUNTIF(source_uk!$B$2:$B$2603,doublecounting!B12) -> 0 | E12: =SIGN(C12*D12) -> 0 | F12: =COUNTIFS(target_uk!$B$2:$B$3030,doublecounting!B12,target_uk!$D$2:$D$3030,1) -> 0 | G12: =COUNTIFS(source_uk!$B$2:$B$2603,doublecounting!B12,source_uk!$D$2:$D$2603,1) -> 0 | H12: =SIGN(F12*G12) -> 0
B13: GB00BJVH7905Summit Utica | C13: =COUNTIF(target_uk!$B$2:$B$3030,doublecounting!B13) -> 1 | D13: =COUNTIF(source_uk!$B$2:$B$2603,doublecounting!B13) -> 0 | E13: =SIGN(C13*D13) -> 0 | F13: =COUNTIFS(target_uk!$B$2:$B$3030,doublecounting!B13,target_uk!$D$2:$D$3030,1) -> 0 | G13: =COUNTIFS(source_uk!$B$2:$B$2603,doublecounting!B13,source_uk!$D$2:$D$2603,1) -> 0 | H13: =SIGN(F13*G13) -> 0
B14: GB0007188757CLP6877L1036 | C14: =COUNTIF(target_uk!$B$2:$B$3030,doublecounting!B14) -> 1 | D14: =COUNTIF(source_uk!$B$2:$B$2603,doublecounting!B14) -> 0 | E14: =SIGN(C14*D14) -> 0 | F14: =COUNTIFS(target_uk!$B$2:$B$3030,doublecounting!B14,target_uk!$D$2:$D$3030,1) -> 1 | G14: =COUNTIFS(source_uk!$B$2:$B$2603,doublecounting!B14,source_uk!$D$2:$D$2603,1) -> 0 | H14: =SIGN(F14*G14) -> 0
... B3579: GB0003463402Jupiter Investment Management Group Ltd. | C3579: =COUNTIF(target_uk!$B$2:$B$3030,doublecounting!B3579) -> 0 | D3579: =COUNTIF(source_uk!$B$2:$B$2603,doublecounting!B3579) -> 2 | E3579: =SIGN(C3579*D3579) -> 0 | F3579: =COUNTIFS(target_uk!$B$2:$B$3030,doublecounting!B3579,target_uk!$D$2:$D$3030,1) -> 0 | G3579: =COUNTIFS(source_uk!$B$2:$B$2603,doublecounting!B3579,source_uk!$D$2:$D$2603,1) -> 0 | H3579: =SIGN(F3579*G3579) -> 0
